Workbook
Name List_Owners: 'Lookup Lists'!$A$5:$A$9
Name List_Priority: 'Lookup Lists'!$B$5:$B$8
Name List_Status: 'Lookup Lists'!$C$5:$C$9
Name List_Teams: 'Lookup Lists'!$D$5:$D$12
Name List_Projects: 'Lookup Lists'!$E$5:$E$10
Name List_Releases: 'Lookup Lists'!$F$5:$F$12
Name List_Sprint: 'Lookup Lists'!$G$5:$G$30
Name List_Phase: 'Lookup Lists'!$H$5:$H$11
Name List_Workstream: 'Lookup Lists'!$I$5:$I$11
Name List_Impact: 'Lookup Lists'!$J$5:$J$7
Name List_Probability: 'Lookup Lists'!$K$5:$K$7
Name List_RiskStatus: 'Lookup Lists'!$L$5:$L$8
Name List_DepStatus: 'Lookup Lists'!$M$5:$M$8
Name List_Category: 'Lookup Lists'!$N$5:$N$10

Sheet Dashboard
A1: FY27 ENGINEERING EXECUTIVE DASHBOARD | P1: CHART DATA (do not delete)
A2: Governance view | 01 Jul 2026 – 30 Jun 2027 | All KPIs formula-linked to Project Tracker · Refresh values by recalculating workbook
P3: Status | Q3: Count
B4: Total Projects | D4: Total Tasks | F4: Completed | H4: In Progress | J4: Blocked | L4: At Risk | P4: Not Started | Q4: =COUNTIF('Project Tracker'!$M$5:$M$113,P4)
B5: =COUNTA('Lookup Lists'!$E$5:$E$10) | D5: =COUNTA('Project Tracker'!$A$5:$A$113) | F5: =COUNTIF('Project Tracker'!$M$5:$M$113,"Completed") | H5: =COUNTIF('Project Tracker'!$M$5:$M$113,"In Progress") | J5: =COUNTIF('Project Tracker'!$M$5:$M$113,"Blocked") | L5: =COUNTIF('Project Tracker'!$M$5:$M$113,"At Risk") | P5: In Progress | Q5: =COUNTIF('Project Tracker'!$M$5:$M$113,P5)
P6: Completed | Q6: =COUNTIF('Project Tracker'!$M$5:$M$113,P6)
B7: Overall Progress % | D7: Hours Planned | F7: Hours Actual | H7: Budget Consumed | J7: Upcoming Milestones | L7: Overdue Dependencies | P7: At Risk | Q7: =COUNTIF('Project Tracker'!$M$5:$M$113,P7)
B8: =IFERROR(AVERAGE('Project Tracker'!$Q$5:$Q$113),0) | D8: =SUM('Project Tracker'!$R$5:$R$113) | F8: =SUM('Project Tracker'!$S$5:$S$113) | H8: =SUM('Project Tracker'!$U$5:$U$113) | J8: =COUNTIF(Milestones!$H$5:$H$27,"YES") | L8: =COUNTIF(Dependencies!$G$5:$G$200,"Overdue") | P8: Blocked | Q8: =COUNTIF('Project Tracker'!$M$5:$M$113,P8)
P11: Owner | Q11: Tasks
P12: Jawahar | Q12: =COUNTIF('Project Tracker'!$J$5:$J$113,P12)
P13: Kadarkarai | Q13: =COUNTIF('Project Tracker'!$J$5:$J$113,P13)
P14: MJ | Q14: =COUNTIF('Project Tracker'!$J$5:$J$113,P14)
P15: Shriguru | Q15: =COUNTIF('Project Tracker'!$J$5:$J$113,P15)
P16: Siva | Q16: =COUNTIF('Project Tracker'!$J$5:$J$113,P16)
P26: Month | Q26: Cumulative Completed % | R26: Planned Burn-up %
P27: 46204 | Q27: =IFERROR(COUNTIFS('Project Tracker'!$M$5:$M$113,"Completed",'Project Tracker'!$O$5:$O$113,"<="&EOMONTH(P27,0))/COUNTA('Project Tracker'!$A$5:$A$113),0) | R27: 0.083333333
P28: 46235 | Q28: =IFERROR(COUNTIFS('Project Tracker'!$M$5:$M$113,"Completed",'Project Tracker'!$O$5:$O$113,"<="&EOMONTH(P28,0))/COUNTA('Project Tracker'!$A$5:$A$113),0) | R28: 0.16666667
P29: 46266 | Q29: =IFERROR(COUNTIFS('Project Tracker'!$M$5:$M$113,"Completed",'Project Tracker'!$O$5:$O$113,"<="&EOMONTH(P29,0))/COUNTA('Project Tracker'!$A$5:$A$113),0) | R29: 0.25
P30: 46296 | Q30: =IFERROR(COUNTIFS('Project Tracker'!$M$5:$M$113,"Completed",'Project Tracker'!$O$5:$O$113,"<="&EOMONTH(P30,0))/COUNTA('Project Tracker'!$A$5:$A$113),0) | R30: 0.33333333
P31: 46327 | Q31: =IFERROR(COUNTIFS('Project Tracker'!$M$5:$M$113,"Completed",'Project Tracker'!$O$5:$O$113,"<="&EOMONTH(P31,0))/COUNTA('Project Tracker'!$A$5:$A$113),0) | R31: 0.41666667
P32: 46357 | Q32: =IFERROR(COUNTIFS('Project Tracker'!$M$5:$M$113,"Completed",'Project Tracker'!$O$5:$O$113,"<="&EOMONTH(P32,0))/COUNTA('Project Tracker'!$A$5:$A$113),0) | R32: 0.5
P33: 46388 | Q33: =IFERROR(COUNTIFS('Project Tracker'!$M$5:$M$113,"Completed",'Project Tracker'!$O$5:$O$113,"<="&EOMONTH(P33,0))/COUNTA('Project Tracker'!$A$5:$A$113),0) | R33: 0.58333333
P34: 46419 | Q34: =IFERROR(COUNTIFS('Project Tracker'!$M$5:$M$113,"Completed",'Project Tracker'!$O$5:$O$113,"<="&EOMONTH(P34,0))/COUNTA('Project Tracker'!$A$5:$A$113),0) | R34: 0.66666667
P35: 46447 | Q35: =IFERROR(COUNTIFS('Project Tracker'!$M$5:$M$113,"Completed",'Project Tracker'!$O$5:$O$113,"<="&EOMONTH(P35,0))/COUNTA('Project Tracker'!$A$5:$A$113),0) | R35: 0.75
P36: 46478 | Q36: =IFERROR(COUNTIFS('Project Tracker'!$M$5:$M$113,"Completed",'Project Tracker'!$O$5:$O$113,"<="&EOMONTH(P36,0))/COUNTA('Project Tracker'!$A$5:$A$113),0) | R36: 0.83333333
P37: 46508 | Q37: =IFERROR(COUNTIFS('Project Tracker'!$M$5:$M$113,"Completed",'Project Tracker'!$O$5:$O$113,"<="&EOMONTH(P37,0))/COUNTA('Project Tracker'!$A$5:$A$113),0) | R37: 0.91666667
P38: 46539 | Q38: =IFERROR(COUNTIFS('Project Tracker'!$M$5:$M$113,"Completed",'Project Tracker'!$O$5:$O$113,"<="&EOMONTH(P38,0))/COUNTA('Project Tracker'!$A$5:$A$113),0) | R38: 1
P42: Release | Q42: Avg % Complete
P43: R26.Q1 | Q43: =IFERROR(AVERAGEIF('Project Tracker'!$Z$5:$Z$113,P43,'Project Tracker'!$Q$5:$Q$113),0)
B44: Resource Utilization (see Resource Planning sheet for heatmap & detail) | P44: R26.Q2 | Q44: =IFERROR(AVERAGEIF('Project Tracker'!$Z$5:$Z$113,P44,'Project Tracker'!$Q$5:$Q$113),0)
B45: Avg Utilization | C45: =IFERROR(AVERAGE('Resource Planning'!$F$5:$F$9),0) | P45: R26.Q3 | Q45: =IFERROR(AVERAGEIF('Project Tracker'!$Z$5:$Z$113,P45,'Project Tracker'!$Q$5:$Q$113),0)
B46: Overallocated Resources | C46: =COUNTIF('Resource Planning'!$I$5:$I$9,"YES") | P46: R26.Q4 | Q46: =IFERROR(AVERAGEIF('Project Tracker'!$Z$5:$Z$113,P46,'Project Tracker'!$Q$5:$Q$113),0)
P47: R27.Q1 | Q47: =IFERROR(AVERAGEIF('Project Tracker'!$Z$5:$Z$113,P47,'Project Tracker'!$Q$5:$Q$113),0)
B48: LINE CHART — Progress trend uses Monthly Burn-up above. | P48: R27.Q2 | Q48: =IFERROR(AVERAGEIF('Project Tracker'!$Z$5:$Z$113,P48,'Project Tracker'!$Q$5:$Q$113),0)
P49: Hotfix | Q49: =IFERROR(AVERAGEIF('Project Tracker'!$Z$5:$Z$113,P49,'Project Tracker'!$Q$5:$Q$113),0)
B50: STATUS LEGEND | D50: HOW TO USE | P50: N/A | Q50: =IFERROR(AVERAGEIF('Project Tracker'!$Z$5:$Z$113,P50,'Project Tracker'!$Q$5:$Q$113),0)
B51: Completed | D51: 1. Update Project Tracker (status, dates, hours) — Dashboard KPIs refresh automatically.
B52: In Progress | D52: 2. Maintain dropdown values on Lookup Lists sheet (named ranges).
B53: At Risk | D53: 3. Review Gantt Chart weekly; orange ▶ marks current week.
B54: Blocked | D54: 4. Clear overdue Dependencies and High/Critical Risks in governance.
B55: Not Started | D55: 5. Print Dashboard / Tracker in Landscape for CTO pack.

Sheet Project Tracker
A1: FY27 ENGINEERING PROJECT TRACKER
A2: Source: plan/FY 27 Draft Planning.xlsx · FY27 V1 | Plan window: 2026-07-01 → 2027-06-30 | Formula-driven | Weekly governance ready
A4: Task ID | B4: Epic | C4: Project | D4: Feature | E4: Sprint | F4: Phase | G4: Workstream | H4: Task Name | I4: Description | J4: Owner | K4: Team | L4: Priority | M4: Status | N4: Start Date | O4: End Date | P4: Duration | Q4: % Complete | R4: Planned Hours | S4: Actual Hours | T4: Variance | U4: Budget | V4: Dependency | W4: Blocked By | X4: Risk | Y4: Next Action | Z4: Target Release | AA4: Remarks | AB4: Critical Path
A5: T-001 | B5: CS 1.0 — Maintenance | C5: CS 1.0 | D5: Maintenance | E5: Sprint 01 | F5: Release | G5: Reliability | H5: Shutting down BRIKS service from Nackle | I5: Pending action to completely remove BRIKS services from Nackle ecosystem | J5: MJ | K5: Core Product | L5: High | M5: At Risk | N5: 46287 | O5: 46293 | P5: =IF(OR(N5="",O5=""),"",O5-N5+1) | Q5: 0.13 | R5: 40 | S5: 5.9 | T5: =S5-R5 | U5: 4400 | X5: R-19 | Y5: Clarify Include/Pending decision; rebaseline if needed | Z5: R26.Q1 | AA5: Include=Yes | Source=FY27 V1 | Timeline=Q1 FY27 | AB5: No
A6: T-002 | B6: CS 1.0 — Maintenance | C6: CS 1.0 | D6: Maintenance | E6: Sprint 02 | F6: Release | G6: Reliability | H6: Shutting Down Coupon/OTP Services | I6: Testing and Any support needed(Ensure all existing application 1X and 2.0 work as expected) | J6: MJ | K6: Core Product | L6: High | M6: In Progress | N6: 46213 | O6: 46226 | P6: =IF(OR(N6="",O6=""),"",O6-N6+1) | Q6: 0.36 | R6: 40 | S6: 14.6 | T6: =S6-R6 | U6: 4400 | V6: T-001 | Y6: Continue sprint commitments; demos Friday | Z6: R26.Q1 | AA6: Include=Yes | Source=FY27 V1 | Timeline=Q1 FY27 | Hours=TBD in source | AB6: No
A7: T-003 | B7: CS 1.0 — Funct Enhance | C7: CS 1.0 | D7: Funct Enhance | E7: Sprint 03 | F7: Design | G7: Product Delivery | H7: Integrate the email validation service for Channel Smart 1.0(Roshni to check) | I7: Handle the self registration and bulk load scneario | J7: MJ | K7: Core Product | L7: High | M7: In Progress | N7: 46236 | O7: 46242 | P7: =IF(OR(N7="",O7=""),"",O7-N7+1) | Q7: 0.36 | R7: 40 | S7: 14 | T7: =S7-R7 | U7: 4400 | V7: T-002 | Y7: Continue sprint commitments; demos Friday | Z7: R26.Q1 | AA7: Include=Yes | Source=FY27 V1 | Timeline=Q1 FY27 | AB7: No
A8: T-004 | B8: CS 1.0 — Funct Enhance | C8: CS 1.0 | D8: Funct Enhance | E8: Sprint 04 | F8: Design | G8: Product Delivery | H8: Build Unsubscribe feature for all the promotional emails(Roshni to check) | I8: Build Unsubscribe feature for all the promotional emails | J8: MJ | K8: Core Product | L8: High | M8: Not Started | N8: 46235 | O8: 46244 | P8: =IF(OR(N8="",O8=""),"",O8-N8+1) | Q8: 0 | R8: 60 | S8: 0 | T8: =S8-R8 | U8: 6600 | V8: T-003 | Y8: Confirm kickoff & acceptance criteria | Z8: R26.Q1 | AA8: Include=Yes | Source=FY27 V1 | Timeline=Q1 FY27 | AB8: No
A9: T-005 | B9: CS 1.0 — New Features | C9: CS 1.0 | D9: New Features | E9: Sprint 05 | F9: Build | G9: Product Delivery | H9: Cash + Wallet + Compliance - Integration patch for CS 1.0 | I9: Integrating the Cash/Wallet/Compliance to Existing 1.0 Customers | J9: MJ | K9: Core Product | L9: High | M9: Not Started | N9: 46235 | O9: 46267 | P9: =IF(OR(N9="",O9=""),"",O9-N9+1) | Q9: 0 | R9: 200 | S9: 0 | T9: =S9-R9 | U9: 22000 | V9: T-004 | Y9: Confirm kickoff & acceptance criteria | Z9: R26.Q1 | AA9: Include=Yes | Source=FY27 V1 | Timeline=July | AB9: No
A10: T-006 | B10: CS 2.0 — Funct Enhance | C10: CS 2.0 | D10: Funct Enhance | E10: Sprint 06 | F10: Design | G10: Product Delivery | H10: Build Pipeline for Achievo to be updated | J10: MJ | K10: Core Product | L10: High | M10: Not Started | N10: 46282 | O10: 46291 | P10: =IF(OR(N10="",O10=""),"",O10-N10+1) | Q10: 0 | R10: 40 | S10: 0 | T10: =S10-R10 | U10: 4400 | Y10: Confirm kickoff & acceptance criteria | Z10: R26.Q1 | AA10: Include=Yes | Source=FY27 V1 | Timeline=July | Hours=TBD in source | AB10: No
A11: T-007 | B11: CS 2.0 — Funct Enhance | C11: CS 2.0 | D11: Funct Enhance | E11: Sprint 01 | F11: Design | G11: Product Delivery | H11: Integrate the email validation service for Channel Smart 2.0(Roshni to check) | I11: Handle the self registration and bulk load scneario | J11: MJ | K11: Core Product | L11: High | M11: Not Started | N11: 46257 | O11: 46263 | P11: =IF(OR(N11="",O11=""),"",O11-N11+1) | Q11: 0 | R11: 40 | S11: 0 | T11: =S11-R11 | U11: 4400 | V11: T-006 | Y11: Confirm kickoff & acceptance criteria | Z11: R26.Q1 | AA11: Include=Yes | Source=FY27 V1 | Timeline=Q1 FY27 | AB11: No
A12: T-008 | B12: CS 2.0 — Funct Enhance | C12: CS 2.0 | D12: Funct Enhance | E12: Sprint 02 | F12: Design | G12: Product Delivery | H12: Build Unsubscribe feature for all the promotional emails(Roshni to check) | I12: Build Unsubscribe feature for all the promotional emails | J12: MJ | K12: Core Product | L12: High | M12: Not Started | N12: 46260 | O12: 46269 | P12: =IF(OR(N12="",O12=""),"",O12-N12+1) | Q12: 0 | R12: 60 | S12: 0 | T12: =S12-R12 | U12: 6600 | V12: T-007 | Y12: Confirm kickoff & acceptance criteria | Z12: R26.Q1 | AA12: Include=Yes | Source=FY27 V1 | Timeline=Q1 FY27 | AB12: No
A13: T-009 | B13: CS 2.0 — New Features | C13: CS 2.0 | D13: New Features | E13: Sprint 03 | F13: Build | G13: Product Delivery | H13: ERP Connerctor Service(Saleforce) | J13: MJ | K13: Core Product | L13: High | M13: Not Started | N13: 46204 | O13: 46261 | P13: =IF(OR(N13="",O13=""),"",O13-N13+1) | Q13: 0 | R13: 350 | S13: 0 | T13: =S13-R13 | U13: 38500 | V13: T-008 | Y13: Confirm kickoff & acceptance criteria | Z13: R26.Q1 | AA13: Include=Yes | Source=FY27 V1 | Timeline=Q1 FY27 | AB13: No
A14: T-010 | B14: CS 2.0 — Tech Maintenance | C14: CS 2.0 | D14: Tech Maintenance | E14: Sprint 04 | F14: Hypercare | G14: Reliability | H14: Technology refresh | I14: Mandatory adoption of newer tools and frameworks Phoenix - Platform Site Upgrades (Onetime) To 16.x Admin - Platform Site Upgrades (Onetime) To 16.x | J14: Jawahar | K14: Core Product | L14: High | M14: In Progress | N14: 46265 | O14: 46277 | P14: =IF(OR(N14="",O14=""),"",O14-N14+1) | Q14: 0.29 | R14: 80 | S14: 26.3 | T14: =S14-R14 | U14: 8800 | V14: T-009 | Y14: Continue sprint commitments; demos Friday | Z14: R26.Q1 | AA14: Include=Yes | Source=FY27 V1 | Timeline=Q1 FY27 | AB14: No
A15: T-011 | B15: CS 2.0 — Tech Maintenance | C15: CS 2.0 | D15: Tech Maintenance | E15: Sprint 05 | F15: Hypercare | G15: Reliability | H15: Fix for Critical Performance Issue(Claims, File Upload) | I15: Top 10 recommendations and Performance Fix to be applied for the existing high priority issues. | J15: Jawahar | K15: Core Product | L15: High | M15: In Progress | N15: 46271 | O15: 46284 | P15: =IF(OR(N15="",O15=""),"",O15-N15+1) | Q15: 0.22 | R15: 40 | S15: 9.5 | T15: =S15-R15 | U15: 4400 | V15: T-010 | Y15: Continue sprint commitments; demos Friday | Z15: R26.Q1 | AA15: Include=Yes | Source=FY27 V1 | Timeline=July | Hours=TBD in source | AB15: No
A16: T-012 | B16: CS 2.0 — New Features | C16: CS 2.0 | D16: New Features | E16: Sprint 06 | F16: Build | G16: Product Delivery | H16: Build a game engine - Requirements | I16: N/A | J16: MJ | K16: Core Product | L16: High | M16: Not Started | N16: 46208 | O16: 46217 | P16: =IF(OR(N16="",O16=""),"",O16-N16+1) | Q16: 0 | R16: 60 | S16: 0 | T16: =S16-R16 | U16: 6600 | V16: T-011 | Y16: Confirm kickoff & acceptance criteria | Z16: R26.Q1 | AA16: Include=Yes | Source=FY27 V1 | Timeline=Q1 FY27 | AB16: No
A17: T-013 | B17: CS 2.0 — New Features | C17: CS 2.0 | D17: New Features | E17: Sprint 01 | F17: Build | G17: Product Delivery | H17: BRD Composer | I17: BRD Composer | J17: MJ | K17: Core Product | L17: High | M17: In Progress | N17: 46237 | O17: 46286 | P17: =IF(OR(N17="",O17=""),"",O17-N17+1) | Q17: 0.24 | R17: 300 | S17: 76.5 | T17: =S17-R17 | U17: 33000 | V17: T-012 | Y17: Continue sprint commitments; demos Friday | Z17: R26.Q1 | AA17: Include=Yes | Source=FY27 V1 | Timeline=Q1 FY27 | AB17: No
A18: T-014 | B18: CS 2.0 — New Features | C18: CS 2.0 | D18: New Features | E18: Sprint 02 | F18: Build | G18: Product Delivery | H18: Communication connector which can support the Whatsapp and Wechat communicaton bi direction | J18: MJ | K18: Core Product | L18: High | M18: Not Started | N18: 46212 | O18: 46281 | P18: =IF(OR(N18="",O18=""),"",O18-N18+1) | Q18: 0 | R18: 600 | S18: 0 | T18: =S18-R18 | U18: 66000 | V18: T-013 | Y18: Confirm kickoff & acceptance criteria | Z18: R26.Q1 | AA18: Include=Yes | Source=FY27 V1 | Timeline=Q1 FY27 | AB18: No
A19: T-015 | B19: CS 2.0 — New Features | C19: CS 2.0 | D19: New Features | E19: Sprint 13 | F19: Build | G19: Product Delivery | H19: AI-Powered Claim Validation | I19: Introduce AI-assisted claim validation capabilities leveraging intelligent document processing to automate claim ingestion, extraction, validation, routing, and continuous learning. Strategic FY27 initiative under evaluation. | J19: MJ | K19: Core Product | L19: High | M19: Not Started | N19: 46410 | O19: 46419 | P19: =IF(OR(N19="",O19=""),"",O19-N19+1) | Q19: 0 | R19: 40 | S19: 0 | T19: =S19-R19 | U19: 4400 | Y19: Confirm kickoff & acceptance criteria | Z19: R27.Q1 | AA19: Include=Yes | Source=FY27 V1 | Timeline=Q3 FY27 | Hours=TBD in source | AB19: No
A20: T-016 | B20: CS 2.0 — New Features | C20: CS 2.0 | D20: New Features | E20: Sprint 22 | F20: Build | G20: Product Delivery | H20: MDF Budget Management & Incentivization | I20: Develop end-to-end MDF request, approval, budget allocation, campaign setup, and incentive distribution capabilities to improve fund utilization and business outcome tracking. Strategic FY27 initiative under evaluation. | J20: MJ | K20: Core Product | L20: High | M20: At Risk | N20: 46535 | O20: 46544 | P20: =IF(OR(N20="",O20=""),"",O20-N20+1) | Q20: 0.09 | R20: 40 | S20: 3.4 | T20: =S20-R20 | U20: 4400 | V20: T-015 | X20: R-14 | Y20: Clarify Include/Pending decision; rebaseline if needed | Z20: N/A | AA20: Include=Pending | Source=FY27 V1 | Timeline=TBD FY27 | Hours=TBD in source | AB20: No
A21: T-017 | B21: CS 2.0 — New Features | C21: CS 2.0 | D21: New Features | E21: Sprint 23 | F21: Build | G21: Product Delivery | H21: AI Display Audit & Compliance Management | I21: Implement AI-powered image analysis to automate display compliance audits, validate merchandising standards, and improve audit scalability, accuracy, and efficiency. Strategic FY27 initiative under evaluation. | J21: MJ | K21: Core Product | L21: High | M21: Blocked | N21: 46482 | O21: 46509 | P21: =IF(OR(N21="",O21=""),"",O21-N21+1) | Q21: 0.14 | R21: 40 | S21: 5.6 | T21: =S21-R21 | U21: 4400 | V21: T-016 | W21: T-016 | X21: R-20 | Y21: Resolve blocker with dependency owner | Z21: N/A | AA21: Include=Pending | Source=FY27 V1 | Timeline=TBD FY27 | Hours=TBD in source | AB21: No
A22: T-018 | B22: CS 2.0 — New Features | C22: CS 2.0 | D22: New Features | E22: Sprint 24 | F22: Build | G22: Product Delivery | H22: Organization-Centric Loyalty Journey | I22: Enable partner organizations to participate in loyalty and incentive programs through organization onboarding, governance controls, centralized reward management, and organization-led participation models. Strategic FY27 initiative under evaluation. | J22: MJ | K22: Core Product | L22: High | M22: At Risk | N22: 46500 | O22: 46527 | P22: =IF(OR(N22="",O22=""),"",O22-N22+1) | Q22: 0.05 | R22: 40 | S22: 1.9 | T22: =S22-R22 | U22: 4400 | V22: T-017 | X22: R-09 | Y22: Clarify Include/Pending decision; rebaseline if needed | Z22: N/A | AA22: Include=Pending | Source=FY27 V1 | Timeline=TBD FY27 | Hours=TBD in source | AB22: No
A23: T-019 | B23: CS 2.0 — New Features | C23: CS 2.0 | D23: New Features | E23: Sprint 25 | F23: Build | G23: Product Delivery | H23: Social Advocacy & Partner Influence Platform | I23: Enable partners to share approved brand content, track engagement and attribution, and participate in incentive-driven advocacy programs that extend brand reach and influence. Strategic FY27 initiative under evaluation. | J23: MJ | K23: Core Product | L23: High | M23: At Risk | N23: 46500 | O23: 46520 | P23: =IF(OR(N23="",O23=""),"",O23-N23+1) | Q23: 0.2 | R23: 40 | S23: 7.7 | T23: =S23-R23 | U23: 4400 | V23: T-018 | X23: R-09 | Y23: Clarify Include/Pending decision; rebaseline if needed | Z23: N/A | AA23: Include=Pending | Source=FY27 V1 | Timeline=TBD FY27 | Hours=TBD in source | AB23: No
A24: T-020 | B24: CS 2.0 — New Features | C24: CS 2.0 | D24: New Features | E24: Sprint 26 | F24: Build | G24: Product Delivery | H24: Partner Referral & Growth Engine | I24: Establish a referral ecosystem with attribution tracking, milestone-based rewards, referral analytics, and conversion visibility to support partner-led acquisition and network-driven growth. Strategic FY27 initiative under evaluation. | J24: MJ | K24: Core Product | L24: High | M24: At Risk | N24: 46544 | O24: 46553 | P24: =IF(OR(N24="",O24=""),"",O24-N24+1) | Q24: 0.12 | R24: 40 | S24: 4.3 | T24: =S24-R24 | U24: 4400 | V24: T-019 | X24: R-18 | Y24: Clarify Include/Pending decision; rebaseline if needed | Z24: N/A | AA24: Include=Pending | Source=FY27 V1 | Timeline=TBD FY27 | Hours=TBD in source | AB24: No
A25: T-021 | B25: CS 2.0 — New Features | C25: CS 2.0 | D25: New Features | E25: Sprint 26 | F25: Build | G25: Product Delivery | H25: AI-Powered Audience Segmentation | I25: Enable business users to create audience segments using natural language queries across transactional, behavioral, and engagement data, improving campaign targeting and intervention effectiveness. Strategic FY27 initiative under evaluation. | J25: MJ | K25: Core Product | L25: High | M25: At Risk | N25: 46513 | O25: 46540 | P25: =IF(OR(N25="",O25=""),"",O25-N25+1) | Q25: 0.07 | R25: 40 | S25: 2.7 | T25: =S25-R25 | U25: 4400 | V25: T-020 | X25: R-02 | Y25: Clarify Include/Pending decision; rebaseline if needed | Z25: N/A | AA25: Include=Pending | Source=FY27 V1 | Timeline=TBD FY27 | Hours=TBD in source | AB25: No
A26: T-022 | B26: CS 2.0 — New Features | C26: CS 2.0 | D26: New Features | E26: Sprint 22 | F26: Build | G26: Product Delivery | H26: Embedded Gamification Experiences | I26: Introduce contextual, embedded gaming experiences within partner journeys to increase engagement, accelerate reward cycles, encourage repeat interactions, and improve program participation. Strategic FY27 initiative under evaluation. | J26: MJ | K26: Core Product | L26: High | M26: At Risk | N26: 46528 | O26: 46537 | P26: =IF(OR(N26="",O26=""),"",O26-N26+1) | Q26: 0.15 | R26: 40 | S26: 6.2 | T26: =S26-R26 | U26: 4400 | V26: T-021 | X26: R-06 | Y26: Clarify Include/Pending decision; rebaseline if needed | Z26: N/A | AA26: Include=Pending | Source=FY27 V1 | Timeline=TBD FY27 | Hours=TBD in source | AB26: No
A27: T-023 | B27: CS 2.0 Achievo — Funct Enhance | C27: CS 2.0 Achievo | D27: Funct Enhance | E27: Sprint 03 | F27: Design | G27: Product Delivery | H27: Achievo - UI/UX Improvements | I27: UI/UX improvements based on External recommendations | J27: Shriguru | K27: Rewards | L27: Critical | M27: Not Started | N27: 46236 | O27: 46256 | P27: =IF(OR(N27="",O27=""),"",O27-N27+1) | Q27: 0 | R27: 40 | S27: 0 | T27: =S27-R27 | U27: 4400 | Y27: Confirm kickoff & acceptance criteria | Z27: R26.Q1 | AA27: Include=Yes | Source=FY27 V1 | Timeline=Q1 FY27 | Hours=TBD in source | AB27: No
A28: T-024 | B28: CS 2.0 Achievo — Tech Maintenance | C28: CS 2.0 Achievo | D28: Tech Maintenance | E28: Sprint 04 | F28: Hypercare | G28: Reliability | H28: Achievo - Mobile Performance Improvement.(Analysis) | I28: Overall Mobile Performance Recommendations | J28: Shriguru | K28: Rewards | L28: Critical | M28: In Progress | N28: 46214 | O28: 46218 | P28: =IF(OR(N28="",O28=""),"",O28-N28+1) | Q28: 0.29 | R28: 24 | S28: 6.5 | T28: =S28-R28 | U28: 2640 | V28: T-023 | Y28: Continue sprint commitments; demos Friday | Z28: R26.Q1 | AA28: Include=Yes | Source=FY27 V1 | Timeline=Q1 FY27 | AB28: Yes
A29: T-025 | B29: CS 2.0 Achievo — Tech Maintenance | C29: CS 2.0 Achievo | D29: Tech Maintenance | E29: Sprint 05 | F29: Hypercare | G29: Reliability | H29: Achievo - Mobile Performance Improvement.(Implementation) | I29: Overall Mobile Performance Improvements | J29: Shriguru | K29: Rewards | L29: Critical | M29: In Progress | N29: 46278 | O29: 46287 | P29: =IF(OR(N29="",O29=""),"",O29-N29+1) | Q29: 0.24 | R29: 40 | S29: 8.8 | T29: =S29-R29 | U29: 4400 | V29: T-024 | Y29: Continue sprint commitments; demos Friday | Z29: R26.Q1 | AA29: Include=Yes | Source=FY27 V1 | Timeline=Q1 FY27 | Hours=TBD in source | AB29: Yes
A30: T-026 | B30: CS 2.0 Achievo — Tech Maintenance | C30: CS 2.0 Achievo | D30: Tech Maintenance | E30: Sprint 06 | F30: Hypercare | G30: Reliability | H30: Achievo - Android 16 Upgrade | I30: Achievo - Android 16 Upgrade. | J30: Shriguru | K30: Rewards | L30: High | M30: Not Started | N30: 46265 | O30: 46271 | P30: =IF(OR(N30="",O30=""),"",O30-N30+1) | Q30: 0 | R30: 40 | S30: 0 | T30: =S30-R30 | U30: 4400 | V30: T-025 | Y30: Confirm kickoff & acceptance criteria | Z30: R26.Q1 | AA30: Include=Yes | Source=FY27 V1 | Timeline=Q1 FY27 | AB30: No
A31: T-027 | B31: CS 2.0 Achievo — Tech Maintenance | C31: CS 2.0 Achievo | D31: Tech Maintenance | E31: Sprint 01 | F31: Hypercare | G31: Reliability | H31: Achievo - iOS Updates | I31: N/A | J31: Shriguru | K31: Rewards | L31: High | M31: In Progress | N31: 46219 | O31: 46225 | P31: =IF(OR(N31="",O31=""),"",O31-N31+1) | Q31: 0.11 | R31: 40 | S31: 4.2 | T31: =S31-R31 | U31: 4400 | V31: T-026 | Y31: Continue sprint commitments; demos Friday | Z31: R26.Q1 | AA31: Include=Yes | Source=FY27 V1 | Timeline=Q1 FY27 | AB31: No
A32: T-028 | B32: CS 2.0 Achievo — New Features | C32: CS 2.0 Achievo | D32: New Features | E32: Sprint 23 | F32: Build | G32: Product Delivery | H32: Achievo Mobile Experience Modernization | I32: Modernize Achievo with mobile-native capabilities including push notifications, voice-assisted discovery, enhanced UX, QR-enabled interactions, gamification, and AI-assisted workflows to increase engagement and participation. Strategic FY27 initiative under evaluation. | J32: Shriguru | K32: Rewards | L32: High | M32: At Risk | N32: 46515 | O32: 46528 | P32: =IF(OR(N32="",O32=""),"",O32-N32+1) | Q32: 0.24 | R32: 40 | S32: 10.6 | T32: =S32-R32 | U32: 4400 | V32: T-027 | X32: R-04 | Y32: Clarify Include/Pending decision; rebaseline if needed | Z32: N/A | AA32: Include=Pending | Source=FY27 V1 | Timeline=TBD FY27 | Hours=TBD in source | AB32: No
A33: T-029 | B33: CS 2.0 — Funct Enhance | C33: CS 2.0 | D33: Funct Enhance | E33: Sprint 24 | F33: Design | G33: Product Delivery | H33: Existing Product Backlog and Delivery Priority Items as needed to be added to Core Product | I33: Need to work with Roshni to identify Priority items to be taken into Core | J33: MJ | K33: Core Product | L33: High | M33: Blocked | N33: 46549 | O33: 46558 | P33: =IF(OR(N33="",O33=""),"",O33-N33+1) | Q33: 0.15 | R33: 40 | S33: 6 | T33: =S33-R33 | U33: 4400 | V33: T-022 | W33: T-022 | X33: R-03 | Y33: Resolve blocker with dependency owner | Z33: N/A | AA33: Include=Pending | Source=FY27 V1 | Timeline=TBD FY27 | Hours=TBD in source | AB33: No
A34: T-030 | B34: CS 2.0 Core — Tech Enhance | C34: CS 2.0 Core | D34: Tech Enhance | E34: Sprint 02 | F34: Build | G34: Platform | H34: New UI for platform portal | J34: MJ | K34: Platform | L34: High | M34: Not Started | N34: 46262 | O34: 46288 | P34: =IF(OR(N34="",O34=""),"",O34-N34+1) | Q34: 0 | R34: 160 | S34: 0 | T34: =S34-R34 | U34: 17600 | Y34: Confirm kickoff & acceptance criteria | Z34: R26.Q1 | AA34: Include=Yes | Source=FY27 V1 | Timeline=Q1 FY27 | AB34: No
A35: T-031 | B35: CS 2.0 Core — Tech Enhance | C35: CS 2.0 Core | D35: Tech Enhance | E35: Sprint 03 | F35: Build | G35: Product Delivery | H35: Architecture Proposal: Core + Extension Model for Participant Portals | I35: Define a Core + Extension architecture model for Participant Portals to separate common product capabilities from client-specific customizations. This will help reduce the effort required to apply latest product changes across multiple delivery deployments, minimize the risk of overriding existing client-specific features, and improve maintainability, upgradeability, and release consistency across implementations. | J35: MJ | K35: Platform | L35: Critical | M35: Not Started | N35: 46209 | O35: 46278 | P35: =IF(OR(N35="",O35=""),"",O35-N35+1) | Q35: 0 | R35: 600 | S35: 0 | T35: =S35-R35 | U35: 66000 | V35: T-030 | Y35: Confirm kickoff & acceptance criteria | Z35: R26.Q1 | AA35: Include=Yes | Source=FY27 V1 | Timeline=July | AB35: No
A36: T-032 | B36: CS 2.0 Core — Tech Enhance | C36: CS 2.0 Core | D36: Tech Enhance | E36: Sprint 04 | F36: Build | G36: Product Delivery | H36: File Upload Module Stabilization and Validation Enhancements (Check if it can be moved to Q2) | I36: Enhance the existing File Upload Module with improved validation, tracking, retry handling, and stabilization capabilities. This will improve upload reliability, reduce processing failures, provide better visibility into upload status, support controlled reprocessing, and strengthen the overall stability of file-based data ingestion. | J36: MJ | K36: Platform | L36: Critical | M36: Not Started | N36: 46215 | O36: 46284 | P36: =IF(OR(N36="",O36=""),"",O36-N36+1) | Q36: 0 | R36: 600 | S36: 0 | T36: =S36-R36 | U36: 66000 | V36: T-031 | Y36: Confirm kickoff & acceptance criteria | Z36: R26.Q1 | AA36: Include=Yes | Source=FY27 V1 | Timeline=July | AB36: No
A37: T-033 | B37: CS 2.0 Core — Tech Maintenance | C37: CS 2.0 Core | D37: Tech Maintenance | E37: Sprint 05 | F37: Hypercare | G37: Reliability | H37: Release Governance, Code Merge and Deployment Control | I37: Standardize the code merge and release management process by improving version control, conflict handling, release planning, approvals, deployment tracking, rollback governance, and client-specific patch management. This will strengthen engineering governance, reduce release risks, and improve operational control across releases. | J37: Jawahar | K37: Platform | L37: High | M37: In Progress | N37: 46243 | O37: 46279 | P37: =IF(OR(N37="",O37=""),"",O37-N37+1) | Q37: 0.22 | R37: 220 | S37: 43.9 | T37: =S37-R37 | U37: 24200 | V37: T-032 | Y37: Continue sprint commitments; demos Friday | Z37: R26.Q1 | AA37: Include=Yes | Source=FY27 V1 | Timeline=Q1 FY27 | AB37: No
A38: T-034 | B38: CS 2.0 Core — Tech Maintenance | C38: CS 2.0 Core | D38: Tech Maintenance | E38: Sprint 06 | F38: Hypercare | G38: Reliability | H38: Achievo Mobile App Upgrades and Store Policy Compliance Updates | I38: Perform Achievo mobile app upgrades and store-specific policy updates for iOS and Android. This includes updating SDKs, dependencies, build tools, privacy/permission declarations, App Store and Play Store compliance requirements, testing, build validation, and supporting app submission/review activities. | J38: Jawahar | K38: Platform | L38: Critical | M38: Not Started | N38: 46225 | O38: 46277 | P38: =IF(OR(N38="",O38=""),"",O38-N38+1) | Q38: 0 | R38: 320 | S38: 0 | T38: =S38-R38 | U38: 35200 | V38: T-033 | Y38: Confirm kickoff & acceptance criteria | Z38: R26.Q1 | AA38: Include=Yes | Source=FY27 V1 | Timeline=Q1 FY27 | AB38: No
A39: T-035 | B39: CS 2.0 Core — Tech Maintenance | C39: CS 2.0 Core | D39: Tech Maintenance | E39: Sprint 01 | F39: Hypercare | G39: Reliability | H39: Next.js 16.x LTS Upgrade for Admin Console and Platform Web Apps | I39: Upgrade Next.js to Version 16.x LTS (Admin & Platform) - 14.X is already outdated and 15.x is reaching end of life by 21/Oct/2026 | J39: Jawahar | K39: Platform | L39: Critical | M39: Not Started | N39: 46256 | O39: 46292 | P39: =IF(OR(N39="",O39=""),"",O39-N39+1) | Q39: 0 | R39: 220 | S39: 0 | T39: =S39-R39 | U39: 24200 | V39: T-034 | Y39: Confirm kickoff & acceptance criteria | Z39: R26.Q1 | AA39: Include=Yes | Source=FY27 V1 | Timeline=July | AB39: No
A40: T-036 | B40: CS 2.0 Core — Tech Enhance | C40: CS 2.0 Core | D40: Tech Enhance | E40: Sprint 02 | F40: Build | G40: Platform | H40: Scalable File Upload Processing Enhancement | I40: Enhance the existing file upload processing architecture to handle large files with more than 100,000 records. This will address the current single-pod stateful processing limitation by improving scalability, reliability, and fault tolerance for high-volume uploads | J40: MJ | K40: Platform | L40: Critical | M40: Not Started | N40: 46226 | O40: 46255 | P40: =IF(OR(N40="",O40=""),"",O40-N40+1) | Q40: 0 | R40: 180 | S40: 0 | T40: =S40-R40 | U40: 19800 | V40: T-035 | Y40: Confirm kickoff & acceptance criteria | Z40: R26.Q1 | AA40: Include=Yes | Source=FY27 V1 | Timeline=Q1 FY27 | AB40: No
A41: T-037 | B41: CS 2.0 Core — Tech Enhance | C41: CS 2.0 Core | D41: Tech Enhance | E41: Sprint 03 | F41: Build | G41: Product Delivery | H41: AWS Secrets Manager Enforcement for Service Credentials | I41: Enforce AWS Secrets Manager usage for all service credentials and remove any plain-text or insecure storage of credentials from configuration files, environment variables, deployment scripts, and service-level settings. This will improve credential security, strengthen governance, reduce secret exposure risk, and align services with secure configuration management practices. | J41: MJ | K41: Platform | L41: Critical | M41: In Progress | N41: 46209 | O41: 46235 | P41: =IF(OR(N41="",O41=""),"",O41-N41+1) | Q41: 0.42 | R41: 160 | S41: 58.7 | T41: =S41-R41 | U41: 17600 | V41: T-036 | X41: R-01 | Y41: Continue sprint commitments; demos Friday | Z41: R26.Q1 | AA41: Include=Yes | Source=FY27 V1 | Timeline=Q1 FY27 | AB41: Yes
A42: T-038 | B42: CS 2.0 Core — Tech Maintenance | C42: CS 2.0 Core | D42: Tech Maintenance | E42: Sprint 04 | F42: Hypercare | G42: Reliability | H42: SAST Vulnerability Fixes Based on GitLab Security Findings | I42: SAST Fixes - As per the GitLab analysis results - Review and fix SAST vulnerabilities reported through GitLab security scans for the existing codebase. Although new vulnerabilities are controlled through MR-level gates, additional findings may arise from updated scan rules, new CVEs, dependency changes, or existing code risks. This includes validation, prioritization, remediation, retesting, and closure tracking in GitLab. | J42: Jawahar | K42: Platform | L42: Critical | M42: In Progress | N42: 46233 | O42: 46252 | P42: =IF(OR(N42="",O42=""),"",O42-N42+1) | Q42: 0.29 | R42: 120 | S42: 35.9 | T42: =S42-R42 | U42: 13200 | V42: T-037 | Y42: Continue sprint commitments; demos Friday | Z42: R26.Q1 | AA42: Include=Yes | Source=FY27 V1 | Timeline=July | AB42: Yes
A43: T-039 | B43: CS 2.0 Core — Tech Maintenance | C43: CS 2.0 Core | D43: Tech Maintenance | E43: Sprint 05 | F43: Hypercare | G43: Reliability | H43: Kubernetes Resource Optimization | I43: Review EKS resource requests/limits, autoscaling, pod disruption budgets, node utilization, and cost/performance tuning. | J43: Jawahar | K43: Platform | L43: Critical | M43: In Progress | N43: 46265 | O43: 46284 | P43: =IF(OR(N43="",O43=""),"",O43-N43+1) | Q43: 0.34 | R43: 120 | S43: 39.2 | T43: =S43-R43 | U43: 13200 | V43: T-038 | X43: R-18 | Y43: Continue sprint commitments; demos Friday | Z43: R26.Q1 | AA43: Include=Yes | Source=FY27 V1 | Timeline=Q1 FY27 | AB43: Yes
A44: T-040 | B44: CS 2.0 Core — Tech Maintenance | C44: CS 2.0 Core | D44: Tech Maintenance | E44: Sprint 06 | F44: Hypercare | G44: Reliability | H44: Infrastructure and Application Monitoring for EKS Platform | I44: Infrastructure and Application Monitoring - Monitor the AWS EKS-based infrastructure and application ecosystem using Grafana and related monitoring tools. This includes tracking cluster health, service availability, resource usage, application performance, API response times, worker status, error trends, and alerts, along with coordinating corrective actions to maintain platform stability and availability. | J44: Jawahar | K44: Platform | L44: Critical | M44: In Progress | N44: 46239 | O44: 46254 | P44: =IF(OR(N44="",O44=""),"",O44-N44+1) | Q44: 0.3 | R44: 96 | S44: 25.9 | T44: =S44-R44 | U44: 10560 | V44: T-039 | Y44: Continue sprint commitments; demos Friday | Z44: R26.Q1 | AA44: Include=Yes | Source=FY27 V1 | Timeline=Q1 FY27 | AB44: Yes
A45: T-041 | B45: CS 2.0 Core — Tech Maintenance | C45: CS 2.0 Core | D45: Tech Maintenance | E45: Sprint 01 | F45: Hypercare | G45: Reliability | H45: Application Issue Fixes and Remediation | I45: Issue Fixes - Analyse and fix application issues reported by delivery, internal, QA, or support teams outside planned feature implementation. This includes root cause analysis, required code/configuration fixes, validation, retesting support, and release through the planned delivery process. | J45: Jawahar | K45: Platform | L45: Critical | M45: In Progress | N45: 46221 | O45: 46290 | P45: =IF(OR(N45="",O45=""),"",O45-N45+1) | Q45: 0.41 | R45: 420 | S45: 197.1 | T45: =S45-R45 | U45: 46200 | V45: T-040 | Y45: Continue sprint commitments; demos Friday | Z45: R26.Q1 | AA45: Include=Yes | Source=FY27 V1 | Timeline=Q1 FY27 | AB45: Yes
A46: T-042 | B46: CS 2.0 Core — Tech Maintenance | C46: CS 2.0 Core | D46: Tech Maintenance | E46: Sprint 02 | F46: Hypercare | G46: Reliability | H46: GitLab DAST Enablement for Web Application and Admin Console | I46: Enable DAST for all the deployable services - Enable GitLab DAST for the Web Application and Admin Console to perform runtime vulnerability scanning as part of the GitLab DevSecOps pipeline. This will help identify security issues in deployed application flows and improve release-level security validation | J46: Jawahar | K46: Platform | L46: High | M46: Not Started | N46: 46242 | O46: 46248 | P46: =IF(OR(N46="",O46=""),"",O46-N46+1) | Q46: 0 | R46: 40 | S46: 0 | T46: =S46-R46 | U46: 4400 | V46: T-041 | Y46: Confirm kickoff & acceptance criteria | Z46: R26.Q1 | AA46: Include=Yes | Source=FY27 V1 | Timeline=Q1 FY27 | AB46: No
A47: T-043 | B47: CS 2.0 Core — Tech Maintenance | C47: CS 2.0 Core | D47: Tech Maintenance | E47: Sprint 03 | F47: Hypercare | G47: Reliability | H47: Release Management, Regression Testing and Test Automation | I47: Release Management Activities - Regression Testing & Automation - Manage release activities, coordinate deployments, perform regression testing, maintain automation scripts, validate fixes, support release sign-off, and monitor post-release stability. This includes improving regression automation coverage to reduce manual effort and improve release quality. Note: Reduced this effort considering the release maangement will also go to the respective features, for the delivery customization this will be part of the delivery budget | J47: Kadarkarai | K47: Platform | L47: Critical | M47: Not Started | N47: 46269 | O47: 46293 | P47: =IF(OR(N47="",O47=""),"",O47-N47+1) | Q47: 0 | R47: 150 | S47: 0 | T47: =S47-R47 | U47: 16500 | V47: T-042 | X47: R-03 | Y47: Confirm kickoff & acceptance criteria | Z47: R26.Q1 | AA47: Include=Yes | Source=FY27 V1 | Timeline=Q1 FY27 | AB47: No
A48: T-044 | B48: CS 2.0 Core — Tech Maintenance | C48: CS 2.0 Core | D48: Tech Maintenance | E48: Sprint 04 | F48: Hypercare | G48: Reliability | H48: Performance Testing, Tuning and Test Suite Management | I48: Perform performance testing as per the planned test schedule, followed by performance fine-tuning, regression testing, test suite maintenance, fixture updates, and automation improvements. This includes adding or removing test fixtures, maintaining test scripts, validating performance improvements, and ensuring the test suite remains aligned with application changes. Note: Reduced this effort considering the release maangement will also go to the respective features | J48: Kadarkarai | K48: Platform | L48: High | M48: Not Started | N48: 46223 | O48: 46247 | P48: =IF(OR(N48="",O48=""),"",O48-N48+1) | Q48: 0 | R48: 150 | S48: 0 | T48: =S48-R48 | U48: 16500 | V48: T-043 | Y48: Confirm kickoff & acceptance criteria | Z48: R26.Q1 | AA48: Include=Yes | Source=FY27 V1 | Timeline=Q1 FY27 | AB48: No
A49: T-045 | B49: CS 2.0 Core — Tech Maintenance | C49: CS 2.0 Core | D49: Tech Maintenance | E49: Sprint 05 | F49: Hypercare | G49: Reliability | H49: DevOps Management, Improvements and Pipeline Monitoring | I49: Devops Management/Improvement/Monitoring - Manage and improve the existing DevOps setup by enhancing CI/CD pipelines, adding new deployment workflows, optimizing automation, monitoring pipeline health, troubleshooting deployment issues, and supporting DevOps changes required for new services, environments, and platform upgrades. | J49: Jawahar | K49: Platform | L49: Critical | M49: Not Started | N49: 46246 | O49: 46251 | P49: =IF(OR(N49="",O49=""),"",O49-N49+1) | Q49: 0 | R49: 36 | S49: 0 | T49: =S49-R49 | U49: 3960 | V49: T-044 | Y49: Confirm kickoff & acceptance criteria | Z49: R26.Q1 | AA49: Include=Yes | Source=FY27 V1 | Timeline=Q1 FY27 | AB49: No
A50: T-046 | B50: CS 2.0 Core — Tech Maintenance | C50: CS 2.0 Core | D50: Tech Maintenance | E50: Sprint 06 | F50: Hypercare | G50: Reliability | H50: Release Based Feature Documentation | I50: Create release based feature documentation covering new features, functional changes, configuration steps, usage flows, dependencies, screenshots, and known limitations. This will support delivery, QA, support, product, and implementation teams in understanding and adopting each release | J50: Jawahar | K50: Platform | L50: Critical | M50: Not Started | N50: 46211 | O50: 46216 | P50: =IF(OR(N50="",O50=""),"",O50-N50+1) | Q50: 0 | R50: 36 | S50: 0 | T50: =S50-R50 | U50: 3960 | V50: T-045 | Y50: Confirm kickoff & acceptance criteria | Z50: R26.Q1 | AA50: Include=Yes | Source=FY27 V1 | Timeline=Q1 FY27 | AB50: No
A51: T-047 | B51: CS 2.0 Core — Tech Maintenance | C51: CS 2.0 Core | D51: Tech Maintenance | E51: Sprint 01 | F51: Hypercare | G51: Reliability | H51: Monthly Library Upgrade Assessment and Remediation Across Services | I51: Perform monthly scheduled library and package upgrade assessment across 20+ services, including web apps, Node.js services, workers, and .NET services. This includes identifying available upgrades, assessing security and compatibility impact, handling breaking changes, applying required fixes, validating builds, and supporting regression/release readiness. | J51: Jawahar | K51: Platform | L51: Critical | M51: In Progress | N51: 46219 | O51: 46223 | P51: =IF(OR(N51="",O51=""),"",O51-N51+1) | Q51: 0.34 | R51: 30 | S51: 10.5 | T51: =S51-R51 | U51: 3300 | V51: T-046 | Y51: Continue sprint commitments; demos Friday | Z51: R26.Q1 | AA51: Include=Yes | Source=FY27 V1 | Timeline=Q1 FY27 | AB51: Yes
A52: T-048 | B52: CS 2.0 Core — Tech Maintenance | C52: CS 2.0 Core | D52: Tech Maintenance | E52: Sprint 02 | F52: Hypercare | G52: Reliability | H52: Cloud Usage Chargeback Model, Monthly Tenant-Level Allocation | I52: Cloud Usage Charge back model (Monthly) - Prepare monthly tenant-level cloud usage chargeback by collecting cloud consumption data, applying agreed allocation rules, validating usage/cost anomalies, and publishing the monthly chargeback summary for each tenant. | J52: Jawahar | K52: Platform | L52: Critical | M52: In Progress | N52: 46214 | O52: 46218 | P52: =IF(OR(N52="",O52=""),"",O52-N52+1) | Q52: 0.25 | R52: 12 | S52: 2.8 | T52: =S52-R52 | U52: 1320 | V52: T-047 | X52: R-20 | Y52: Continue sprint commitments; demos Friday | Z52: R26.Q1 | AA52: Include=Yes | Source=FY27 V1 | Timeline=Q1 FY27 | AB52: Yes
A53: T-049 | B53: CS 2.0 Core — Tech Maintenance | C53: CS 2.0 Core | D53: Tech Maintenance | E53: Sprint 07 | F53: Hypercare | G53: Reliability | H53: Internal VAPT - Half-Yearly Penetration Testing and Fixes | I53: Perform half-yearly internal VAPT between yearly external VAPT cycles to proactively identify and fix security issues. This includes internal penetration testing, finding validation, severity-based prioritization, remediation, retesting support, and closure tracking. | J53: Jawahar | K53: Platform | L53: Critical | M53: Not Started | N53: 46312 | O53: 46328 | P53: =IF(OR(N53="",O53=""),"",O53-N53+1) | Q53: 0 | R53: 100 | S53: 0 | T53: =S53-R53 | U53: 11000 | Y53: Confirm kickoff & acceptance criteria | Z53: R26.Q2 | AA53: Include=Yes | Source=FY27 V1 | Timeline=Q2 FY27 | AB53: No
A54: T-050 | B54: CS 2.0 Core — Tech Enhance | C54: CS 2.0 Core | D54: Tech Enhance | E54: Sprint 08 | F54: Build | G54: Platform | H54: Configuration Migration Tool Enhancement | I54: Enhance the existing Configuration Migration Tool to improve automation, reliability, and control while moving configuration changes across environments and client deployments. This will reduce manual deployment effort, minimize migration errors, improve tenant/environment consistency, and support faster, more governed configuration rollouts. | J54: MJ | K54: Platform | L54: High | M54: Not Started | N54: 46302 | O54: 46341 | P54: =IF(OR(N54="",O54=""),"",O54-N54+1) | Q54: 0 | R54: 240 | S54: 0 | T54: =S54-R54 | U54: 26400 | V54: T-049 | Y54: Confirm kickoff & acceptance criteria | Z54: R26.Q2 | AA54: Include=Yes | Source=FY27 V1 | Timeline=Q2 FY27 | AB54: No
A55: T-051 | B55: CS 2.0 Core — Tech Maintenance | C55: CS 2.0 Core | D55: Tech Maintenance | E55: Sprint 09 | F55: Hypercare | G55: Reliability | H55: Application Issue Fixes and Remediation | I55: Issue Fixes - Analyse and fix application issues reported by delivery, internal, QA, or support teams outside planned feature implementation. This includes root cause analysis, required code/configuration fixes, validation, retesting support, and release through the planned delivery process. | J55: Jawahar | K55: Platform | L55: Critical | M55: Not Started | N55: 46308 | O55: 46377 | P55: =IF(OR(N55="",O55=""),"",O55-N55+1) | Q55: 0 | R55: 420 | S55: 0 | T55: =S55-R55 | U55: 46200 | V55: T-050 | X55: R-01 | Y55: Confirm kickoff & acceptance criteria | Z55: R26.Q2 | AA55: Include=Yes | Source=FY27 V1 | Timeline=Q2 FY27 | AB55: No
A56: T-052 | B56: CS 2.0 Core — Tech Maintenance | C56: CS 2.0 Core | D56: Tech Maintenance | E56: Sprint 10 | F56: Hypercare | G56: Reliability | H56: GitLab DAST Enablement for Web Application and Admin Console | I56: Enable DAST for all the deployable services - Enable GitLab DAST for the Web Application and Admin Console to perform runtime vulnerability scanning as part of the GitLab DevSecOps pipeline. This will help identify security issues in deployed application flows and improve release-level security validation | J56: Jawahar | K56: Platform | L56: High | M56: Not Started | N56: 46307 | O56: 46313 | P56: =IF(OR(N56="",O56=""),"",O56-N56+1) | Q56: 0 | R56: 40 | S56: 0 | T56: =S56-R56 | U56: 4400 | V56: T-051 | Y56: Confirm kickoff & acceptance criteria | Z56: R26.Q2 | AA56: Include=Yes | Source=FY27 V1 | Timeline=Q2 FY27 | AB56: No
A57: T-053 | B57: CS 2.0 Core — Tech Maintenance | C57: CS 2.0 Core | D57: Tech Maintenance | E57: Sprint 11 | F57: Hypercare | G57: Reliability | H57: Release Management, Regression Testing and Test Automation | I57: Release Management Activities - Regression Testing & Automation - Manage release activities, coordinate deployments, perform regression testing, maintain automation scripts, validate fixes, support release sign-off, and monitor post-release stability. This includes improving regression automation coverage to reduce manual effort and improve release quality. Note: Reduced this effort considering the release maangement will also go to the respective features, for the delivery customization this will be part of the delivery budget | J57: Jawahar | K57: Platform | L57: Critical | M57: Not Started | N57: 46343 | O57: 46367 | P57: =IF(OR(N57="",O57=""),"",O57-N57+1) | Q57: 0 | R57: 150 | S57: 0 | T57: =S57-R57 | U57: 16500 | V57: T-052 | Y57: Confirm kickoff & acceptance criteria | Z57: R26.Q2 | AA57: Include=Yes | Source=FY27 V1 | Timeline=Q2 FY27 | AB57: No
A58: T-054 | B58: CS 2.0 Core — Tech Maintenance | C58: CS 2.0 Core | D58: Tech Maintenance | E58: Sprint 12 | F58: Hypercare | G58: Reliability | H58: Performance Testing, Tuning and Test Suite Management | I58: Perform performance testing as per the planned test schedule, followed by performance fine-tuning, regression testing, test suite maintenance, fixture updates, and automation improvements. This includes adding or removing test fixtures, maintaining test scripts, validating performance improvements, and ensuring the test suite remains aligned with application changes. Note: Reduced this effort considering the release maangement will also go to the respective features | J58: Jawahar | K58: Platform | L58: High | M58: Not Started | N58: 46322 | O58: 46346 | P58: =IF(OR(N58="",O58=""),"",O58-N58+1) | Q58: 0 | R58: 150 | S58: 0 | T58: =S58-R58 | U58: 16500 | V58: T-053 | Y58: Confirm kickoff & acceptance criteria | Z58: R26.Q2 | AA58: Include=Yes | Source=FY27 V1 | Timeline=Q2 FY27 | AB58: No
A59: T-055 | B59: CS 2.0 Core — Tech Maintenance | C59: CS 2.0 Core | D59: Tech Maintenance | E59: Sprint 07 | F59: Hypercare | G59: Reliability | H59: DevOps Management, Improvements and Pipeline Monitoring | I59: Devops Management/Improvement/Monitoring - Manage and improve the existing DevOps setup by enhancing CI/CD pipelines, adding new deployment workflows, optimizing automation, monitoring pipeline health, troubleshooting deployment issues, and supporting DevOps changes required for new services, environments, and platform upgrades. | J59: Jawahar | K59: Platform | L59: Critical | M59: Not Started | N59: 46317 | O59: 46322 | P59: =IF(OR(N59="",O59=""),"",O59-N59+1) | Q59: 0 | R59: 36 | S59: 0 | T59: =S59-R59 | U59: 3960 | V59: T-054 | Y59: Confirm kickoff & acceptance criteria | Z59: R26.Q2 | AA59: Include=Yes | Source=FY27 V1 | Timeline=Q2 FY27 | AB59: No
A60: T-056 | B60: CS 2.0 Core — Tech Maintenance | C60: CS 2.0 Core | D60: Tech Maintenance | E60: Sprint 08 | F60: Hypercare | G60: Reliability | H60: Release Based Feature Documentation | I60: Create release based feature documentation covering new features, functional changes, configuration steps, usage flows, dependencies, screenshots, and known limitations. This will support delivery, QA, support, product, and implementation teams in understanding and adopting each release | J60: Jawahar | K60: Platform | L60: Critical | M60: Not Started | N60: 46365 | O60: 46370 | P60: =IF(OR(N60="",O60=""),"",O60-N60+1) | Q60: 0 | R60: 36 | S60: 0 | T60: =S60-R60 | U60: 3960 | V60: T-055 | Y60: Confirm kickoff & acceptance criteria | Z60: R26.Q2 | AA60: Include=Yes | Source=FY27 V1 | Timeline=Q2 FY27 | AB60: No
A61: T-057 | B61: CS 2.0 Core — Tech Maintenance | C61: CS 2.0 Core | D61: Tech Maintenance | E61: Sprint 09 | F61: Hypercare | G61: Reliability | H61: Monthly Library Upgrade Assessment and Remediation Across Services | I61: Perform monthly scheduled library and package upgrade assessment across 20+ services, including web apps, Node.js services, workers, and .NET services. This includes identifying available upgrades, assessing security and compatibility impact, handling breaking changes, applying required fixes, validating builds, and supporting regression/release readiness. | J61: Jawahar | K61: Platform | L61: Critical | M61: Not Started | N61: 46298 | O61: 46302 | P61: =IF(OR(N61="",O61=""),"",O61-N61+1) | Q61: 0 | R61: 30 | S61: 0 | T61: =S61-R61 | U61: 3300 | V61: T-056 | Y61: Confirm kickoff & acceptance criteria | Z61: R26.Q2 | AA61: Include=Yes | Source=FY27 V1 | Timeline=Q2 FY27 | AB61: No
A62: T-058 | B62: CS 2.0 Core — Tech Maintenance | C62: CS 2.0 Core | D62: Tech Maintenance | E62: Sprint 10 | F62: Hypercare | G62: Reliability | H62: Cloud Usage Chargeback Model, Monthly Tenant-Level Allocation | I62: Cloud Usage Charge back model (Monthly) - Prepare monthly tenant-level cloud usage chargeback by collecting cloud consumption data, applying agreed allocation rules, validating usage/cost anomalies, and publishing the monthly chargeback summary for each tenant. | J62: Jawahar | K62: Platform | L62: Critical | M62: Not Started | N62: 46319 | O62: 46323 | P62: =IF(OR(N62="",O62=""),"",O62-N62+1) | Q62: 0 | R62: 12 | S62: 0 | T62: =S62-R62 | U62: 1320 | V62: T-057 | Y62: Confirm kickoff & acceptance criteria | Z62: R26.Q2 | AA62: Include=Yes | Source=FY27 V1 | Timeline=Q2 FY27 | AB62: No
A63: T-059 | B63: CS 2.0 Core — Tech Maintenance | C63: CS 2.0 Core | D63: Tech Maintenance | E63: Sprint 11 | F63: Hypercare | G63: Reliability | H63: Code Refactoring, Dependency Upgrades and Deprecated Code Removal | I63: Improve code quality and maintainability by refactoring existing code, upgrading outdated dependencies, and removing deprecated or unused code/components. This helps reduce technical debt, improve system stability, support security compliance, and keep the application aligned with current technology standards. | J63: Jawahar | K63: Platform | L63: High | M63: Not Started | N63: 46324 | O63: 46363 | P63: =IF(OR(N63="",O63=""),"",O63-N63+1) | Q63: 0 | R63: 240 | S63: 0 | T63: =S63-R63 | U63: 26400 | V63: T-058 | Y63: Confirm kickoff & acceptance criteria | Z63: R26.Q2 | AA63: Include=Yes | Source=FY27 V1 | Timeline=Q2 FY27 | AB63: No
A64: T-060 | B64: CS 2.0 Core — Tech Enhance | C64: CS 2.0 Core | D64: Tech Enhance | E64: Sprint 12 | F64: Build | G64: Product Delivery | H64: Table-Specific Metadata Model Storage Enhancement | I64: Enhance the existing metadata model storage by separating the currently combined JSON structure into table-specific JSON structures. This will improve metadata maintainability, support table level configuration flexibility, reduce complexity, and make future schema or configuration changes easier to manage. | J64: MJ | K64: Platform | L64: High | M64: Not Started | N64: 46354 | O64: 46383 | P64: =IF(OR(N64="",O64=""),"",O64-N64+1) | Q64: 0 | R64: 180 | S64: 0 | T64: =S64-R64 | U64: 19800 | V64: T-059 | Y64: Confirm kickoff & acceptance criteria | Z64: R26.Q2 | AA64: Include=Yes | Source=FY27 V1 | Timeline=Q2 FY27 | AB64: No
A65: T-061 | B65: CS 2.0 Core — Tech Enhance | C65: CS 2.0 Core | D65: Tech Enhance | E65: Sprint 07 | F65: Build | G65: Product Delivery | H65: System Wide AWS Redis Caching Layer Enablement | I65: Extend the existing AWS Redis caching layer, currently used for fraud related processing, to support other time-consuming queries across the system. This will include identifying high-latency and frequently executed queries, defining suitable cache keys and expiry rules, implementing cache read/write logic, and validating performance improvements. The enhancement will help reduce database load, improve response time, and increase overall platform scalability. | J65: MJ | K65: Platform | L65: High | M65: Not Started | N65: 46302 | O65: 46328 | P65: =IF(OR(N65="",O65=""),"",O65-N65+1) | Q65: 0 | R65: 160 | S65: 0 | T65: =S65-R65 | U65: 17600 | V65: T-060 | Y65: Confirm kickoff & acceptance criteria | Z65: R26.Q2 | AA65: Include=Yes | Source=FY27 V1 | Timeline=Q2 FY27 | AB65: No
A66: T-062 | B66: CS 2.0 Core — Tech Enhance | C66: CS 2.0 Core | D66: Tech Enhance | E66: Sprint 08 | F66: Build | G66: Product Delivery | H66: Workflow Engine Observability and Traceability Enhancements | I66: Improve the Workflow Engine with better logging, monitoring, and traceability capabilities. This will help track workflow execution, identify failures faster, improve operational visibility, simplify troubleshooting, and strengthen overall engine reliability and supportability. | J66: MJ | K66: Platform | L66: High | M66: Not Started | N66: 46352 | O66: 46378 | P66: =IF(OR(N66="",O66=""),"",O66-N66+1) | Q66: 0 | R66: 160 | S66: 0 | T66: =S66-R66 | U66: 17600 | V66: T-061 | Y66: Confirm kickoff & acceptance criteria | Z66: R26.Q2 | AA66: Include=Yes | Source=FY27 V1 | Timeline=Q2 FY27 | AB66: No
A67: T-063 | B67: CS 2.0 Core — Tech Enhance | C67: CS 2.0 Core | D67: Tech Enhance | E67: Sprint 09 | F67: Build | G67: Product Delivery | H67: Command and Query Engine Enhancement with GraphQL Evaluation | I67: Enhance the Command and Query Engine by evaluating GraphQL-like querying capabilities and optimizing command/query handling. This will improve technical product capability by supporting more flexible data retrieval, better query control, optimized execution, and clearer separation between write operations and read operations. The activity will also include evaluating whether GraphQL is suitable for the platform based on performance, security, complexity, maintainability, and tenant-specific metadata requirements. | J67: MJ | K67: Platform | L67: High | M67: Not Started | N67: 46334 | O67: 46373 | P67: =IF(OR(N67="",O67=""),"",O67-N67+1) | Q67: 0 | R67: 240 | S67: 0 | T67: =S67-R67 | U67: 26400 | V67: T-062 | Y67: Confirm kickoff & acceptance criteria | Z67: R26.Q2 | AA67: Include=Yes | Source=FY27 V1 | Timeline=Q2 FY27 | AB67: No
... A70: T-066 | B70: CS 2.0 Core — Tech Maintenance | C70: CS 2.0 Core | D70: Tech Maintenance | E70: Sprint 12 | F70: Hypercare | G70: Reliability | H70: Disaster Recovery Drill and Runbook Execution | I70: Perform Disaster Recovery activity as per planned schedule - Perform the scheduled Disaster Recovery activity in the London region by executing the approved DR runbook, validating infrastructure, application, and data availability, coordinating failover/failback activities, documenting observations, and updating the runbook based on the exercise findings. | J70: Jawahar | K70: Platform | L70: Critical | M70: Not Started | N70: 46331 | O70: 46337 | P70: =IF(OR(N70="",O70=""),"",O70-N70+1) | Q70: 0 | R70: 40 | S70: 0 | T70: =S70-R70 | U70: 4400 | V70: T-065 | Y70: Confirm kickoff & acceptance criteria | Z70: R26.Q2 | AA70: Include=Yes | Source=FY27 V1 | Timeline=Q2 FY27 | AB70: No
A71: T-067 | B71: CS 2.0 Core — Tech Maintenance | C71: CS 2.0 Core | D71: Tech Maintenance | E71: Sprint 14 | F71: Hypercare | G71: Reliability | H71: Application Issue Fixes and Remediation | I71: Issue Fixes - Analyse and fix application issues reported by delivery, internal, QA, or support teams outside planned feature implementation. This includes root cause analysis, required code/configuration fixes, validation, retesting support, and release through the planned delivery process. | J71: Jawahar | K71: Platform | L71: Critical | M71: Not Started | N71: 46405 | O71: 46474 | P71: =IF(OR(N71="",O71=""),"",O71-N71+1) | Q71: 0 | R71: 420 | S71: 0 | T71: =S71-R71 | U71: 46200 | Y71: Confirm kickoff & acceptance criteria | Z71: R27.Q1 | AA71: Include=Yes | Source=FY27 V1 | Timeline=Q3 FY27 | AB71: No
A72: T-068 | B72: CS 2.0 Core — Tech Maintenance | C72: CS 2.0 Core | D72: Tech Maintenance | E72: Sprint 15 | F72: Hypercare | G72: Reliability | H72: GitLab DAST Enablement for Web Application and Admin Console | I72: Enable DAST for all the deployable services - Enable GitLab DAST for the Web Application and Admin Console to perform runtime vulnerability scanning as part of the GitLab DevSecOps pipeline. This will help identify security issues in deployed application flows and improve release-level security validation | J72: Jawahar | K72: Platform | L72: High | M72: Not Started | N72: 46413 | O72: 46419 | P72: =IF(OR(N72="",O72=""),"",O72-N72+1) | Q72: 0 | R72: 40 | S72: 0 | T72: =S72-R72 | U72: 4400 | V72: T-067 | Y72: Confirm kickoff & acceptance criteria | Z72: R27.Q1 | AA72: Include=Yes | Source=FY27 V1 | Timeline=Q3 FY27 | AB72: No
A73: T-069 | B73: CS 2.0 Core — Tech Maintenance | C73: CS 2.0 Core | D73: Tech Maintenance | E73: Sprint 16 | F73: Hypercare | G73: Reliability | H73: Release Management, Regression Testing and Test Automation | I73: Release Management Activities - Regression Testing & Automation - Manage release activities, coordinate deployments, perform regression testing, maintain automation scripts, validate fixes, support release sign-off, and monitor post-release stability. This includes improving regression automation coverage to reduce manual effort and improve release quality. Note: Reduced this effort considering the release maangement will also go to the respective features, for the delivery customization this will be part of the delivery budget | J73: Jawahar | K73: Platform | L73: Critical | M73: Not Started | N73: 46400 | O73: 46424 | P73: =IF(OR(N73="",O73=""),"",O73-N73+1) | Q73: 0 | R73: 150 | S73: 0 | T73: =S73-R73 | U73: 16500 | V73: T-068 | X73: R-15 | Y73: Confirm kickoff & acceptance criteria | Z73: R27.Q1 | AA73: Include=Yes | Source=FY27 V1 | Timeline=Q3 FY27 | AB73: No
A74: T-070 | B74: CS 2.0 Core — Tech Maintenance | C74: CS 2.0 Core | D74: Tech Maintenance | E74: Sprint 17 | F74: Hypercare | G74: Reliability | H74: Performance Testing, Tuning and Test Suite Management | I74: Perform performance testing as per the planned test schedule, followed by performance fine-tuning, regression testing, test suite maintenance, fixture updates, and automation improvements. This includes adding or removing test fixtures, maintaining test scripts, validating performance improvements, and ensuring the test suite remains aligned with application changes. Note: Reduced this effort considering the release maangement will also go to the respective features | J74: Jawahar | K74: Platform | L74: High | M74: Not Started | N74: 46444 | O74: 46468 | P74: =IF(OR(N74="",O74=""),"",O74-N74+1) | Q74: 0 | R74: 150 | S74: 0 | T74: =S74-R74 | U74: 16500 | V74: T-069 | Y74: Confirm kickoff & acceptance criteria | Z74: R27.Q1 | AA74: Include=Yes | Source=FY27 V1 | Timeline=Q3 FY27 | AB74: No
A75: T-071 | B75: CS 2.0 Core — Tech Maintenance | C75: CS 2.0 Core | D75: Tech Maintenance | E75: Sprint 18 | F75: Hypercare | G75: Reliability | H75: DevOps Management, Improvements and Pipeline Monitoring | I75: Devops Management/Improvement/Monitoring - Manage and improve the existing DevOps setup by enhancing CI/CD pipelines, adding new deployment workflows, optimizing automation, monitoring pipeline health, troubleshooting deployment issues, and supporting DevOps changes required for new services, environments, and platform upgrades. | J75: Jawahar | K75: Platform | L75: Critical | M75: Not Started | N75: 46434 | O75: 46439 | P75: =IF(OR(N75="",O75=""),"",O75-N75+1) | Q75: 0 | R75: 36 | S75: 0 | T75: =S75-R75 | U75: 3960 | V75: T-070 | Y75: Confirm kickoff & acceptance criteria | Z75: R27.Q1 | AA75: Include=Yes | Source=FY27 V1 | Timeline=Q3 FY27 | AB75: No
A76: T-072 | B76: CS 2.0 Core — Tech Maintenance | C76: CS 2.0 Core | D76: Tech Maintenance | E76: Sprint 13 | F76: Hypercare | G76: Reliability | H76: Release Based Feature Documentation | I76: Create release based feature documentation covering new features, functional changes, configuration steps, usage flows, dependencies, screenshots, and known limitations. This will support delivery, QA, support, product, and implementation teams in understanding and adopting each release | J76: Jawahar | K76: Platform | L76: Critical | M76: Not Started | N76: 46430 | O76: 46435 | P76: =IF(OR(N76="",O76=""),"",O76-N76+1) | Q76: 0 | R76: 36 | S76: 0 | T76: =S76-R76 | U76: 3960 | V76: T-071 | Y76: Confirm kickoff & acceptance criteria | Z76: R27.Q1 | AA76: Include=Yes | Source=FY27 V1 | Timeline=Q3 FY27 | AB76: No
A77: T-073 | B77: CS 2.0 Core — Tech Maintenance | C77: CS 2.0 Core | D77: Tech Maintenance | E77: Sprint 14 | F77: Hypercare | G77: Reliability | H77: Monthly Library Upgrade Assessment and Remediation Across Services | I77: Perform monthly scheduled library and package upgrade assessment across 20+ services, including web apps, Node.js services, workers, and .NET services. This includes identifying available upgrades, assessing security and compatibility impact, handling breaking changes, applying required fixes, validating builds, and supporting regression/release readiness. | J77: Jawahar | K77: Platform | L77: Critical | M77: Not Started | N77: 46469 | O77: 46473 | P77: =IF(OR(N77="",O77=""),"",O77-N77+1) | Q77: 0 | R77: 30 | S77: 0 | T77: =S77-R77 | U77: 3300 | V77: T-072 | Y77: Confirm kickoff & acceptance criteria | Z77: R27.Q1 | AA77: Include=Yes | Source=FY27 V1 | Timeline=Q3 FY27 | AB77: No
A78: T-074 | B78: CS 2.0 Core — Tech Maintenance | C78: CS 2.0 Core | D78: Tech Maintenance | E78: Sprint 15 | F78: Hypercare | G78: Reliability | H78: Cloud Usage Chargeback Model, Monthly Tenant-Level Allocation | I78: Cloud Usage Charge back model (Monthly) - Prepare monthly tenant-level cloud usage chargeback by collecting cloud consumption data, applying agreed allocation rules, validating usage/cost anomalies, and publishing the monthly chargeback summary for each tenant. | J78: Jawahar | K78: Platform | L78: Critical | M78: Not Started | N78: 46452 | O78: 46456 | P78: =IF(OR(N78="",O78=""),"",O78-N78+1) | Q78: 0 | R78: 12 | S78: 0 | T78: =S78-R78 | U78: 1320 | V78: T-073 | Y78: Confirm kickoff & acceptance criteria | Z78: R27.Q1 | AA78: Include=Yes | Source=FY27 V1 | Timeline=Q3 FY27 | AB78: No
A79: T-075 | B79: CS 2.0 Core — Tech Maintenance | C79: CS 2.0 Core | D79: Tech Maintenance | E79: Sprint 16 | F79: Hypercare | G79: Reliability | H79: Yearly External VAPT for Web Application | I79: Perform VAPT for web application as per planned schedule - Perform yearly external VAPT for the Web Application by coordinating with the external security team, providing required access and application details, reviewing reported findings, fixing applicable vulnerabilities, and supporting retesting and closure of identified issues. | J79: Jawahar | K79: Platform | L79: Critical | M79: Not Started | N79: 46401 | O79: 46437 | P79: =IF(OR(N79="",O79=""),"",O79-N79+1) | Q79: 0 | R79: 220 | S79: 0 | T79: =S79-R79 | U79: 24200 | V79: T-074 | Y79: Confirm kickoff & acceptance criteria | Z79: R27.Q1 | AA79: Include=Yes | Source=FY27 V1 | Timeline=Q3 FY27 | AB79: No
A80: T-076 | B80: CS 2.0 Core — Tech Maintenance | C80: CS 2.0 Core | D80: Tech Maintenance | E80: Sprint 17 | F80: Hypercare | G80: Reliability | H80: Yearly External VAPT for Mobile Application | I80: Perform VAPT for mobile application as per planned schedule - Perform yearly external VAPT for both iOS and Android mobile applications by coordinating with the external security team, sharing required app builds and test access, reviewing reported findings, fixing applicable vulnerabilities, and supporting retesting and closure of identified issues. | J80: Jawahar | K80: Platform | L80: Critical | M80: Not Started | N80: 46438 | O80: 46454 | P80: =IF(OR(N80="",O80=""),"",O80-N80+1) | Q80: 0 | R80: 100 | S80: 0 | T80: =S80-R80 | U80: 11000 | V80: T-075 | Y80: Confirm kickoff & acceptance criteria | Z80: R27.Q1 | AA80: Include=Yes | Source=FY27 V1 | Timeline=Q3 FY27 | AB80: No
A81: T-077 | B81: CS 2.0 Core — Tech Enhance | C81: CS 2.0 Core | D81: Tech Enhance | E81: Sprint 18 | F81: Build | G81: Platform | H81: Form Builder Decoupling into Standalone NPM Package | I81: Decouple the existing Form Builder from the Next.js codebase and convert it into a standalone reusable NPM package. This will improve modularity, enable reuse across multiple applications, reduce dependency on the main codebase, simplify maintenance, and support independent versioning and release management for Form Builder changes. | J81: MJ | K81: Platform | L81: Medium | M81: Not Started | N81: 46412 | O81: 46434 | P81: =IF(OR(N81="",O81=""),"",O81-N81+1) | Q81: 0 | R81: 140 | S81: 0 | T81: =S81-R81 | U81: 15400 | V81: T-076 | Y81: Confirm kickoff & acceptance criteria | Z81: R27.Q1 | AA81: Include=No | Source=FY27 V1 | Timeline=Q3 FY27 | AB81: No
A82: T-078 | B82: CS 2.0 Core — Tech Enhance | C82: CS 2.0 Core | D82: Tech Enhance | E82: Sprint 13 | F82: Build | G82: Product Delivery | H82: View Builder Governance and Performance Enhancement | I82: Enhance the existing View Builder to improve usability, performance, and governance. This includes introducing controls to manage excessive view creation, optimizing view execution, improving user experience, defining limits or approval rules where required, and reducing the risk of performance issues caused by unmanaged or duplicate user-created views. | J82: MJ | K82: Platform | L82: Medium | M82: Not Started | N82: 46398 | O82: 46444 | P82: =IF(OR(N82="",O82=""),"",O82-N82+1) | Q82: 0 | R82: 280 | S82: 0 | T82: =S82-R82 | U82: 30800 | V82: T-077 | Y82: Confirm kickoff & acceptance criteria | Z82: R27.Q1 | AA82: Include=Yes | Source=FY27 V1 | Timeline=Q3 FY27 | AB82: No
A83: T-079 | B83: CS 2.0 Core — Tech Enhance | C83: CS 2.0 Core | D83: Tech Enhance | E83: Sprint 14 | F83: Build | G83: Product Delivery | H83: Application Health Monitoring Dashboard | I83: Build an in-application health monitoring page to provide visibility into the status of key services outside Grafana. This will help product, support, and operations teams quickly monitor service availability, dependency health, API status, worker status, and critical system indicators directly from the application. | J83: MJ | K83: Platform | L83: Medium | M83: Not Started | N83: 46388 | O83: 46437 | P83: =IF(OR(N83="",O83=""),"",O83-N83+1) | Q83: 0 | R83: 300 | S83: 0 | T83: =S83-R83 | U83: 33000 | V83: T-078 | Y83: Confirm kickoff & acceptance criteria | Z83: R27.Q1 | AA83: Include=No | Source=FY27 V1 | Timeline=Q3 FY27 | AB83: No
A84: T-080 | B84: CS 2.0 Core — Tech Maintenance | C84: CS 2.0 Core | D84: Tech Maintenance | E84: Sprint 19 | F84: Hypercare | G84: Reliability | H84: Application Issue Fixes and Remediation | I84: Issue Fixes - Analyse and fix application issues reported by delivery, internal, QA, or support teams outside planned feature implementation. This includes root cause analysis, required code/configuration fixes, validation, retesting support, and release through the planned delivery process. | J84: Jawahar | K84: Platform | L84: Critical | M84: Not Started | N84: 46489 | O84: 46558 | P84: =IF(OR(N84="",O84=""),"",O84-N84+1) | Q84: 0 | R84: 420 | S84: 0 | T84: =S84-R84 | U84: 46200 | Y84: Confirm kickoff & acceptance criteria | Z84: R27.Q2 | AA84: Include=Yes | Source=FY27 V1 | Timeline=Q4 FY27 | AB84: No
A85: T-081 | B85: CS 2.0 Core — Tech Maintenance | C85: CS 2.0 Core | D85: Tech Maintenance | E85: Sprint 20 | F85: Hypercare | G85: Reliability | H85: GitLab DAST Enablement for Web Application and Admin Console | I85: Enable DAST for all the deployable services - Enable GitLab DAST for the Web Application and Admin Console to perform runtime vulnerability scanning as part of the GitLab DevSecOps pipeline. This will help identify security issues in deployed application flows and improve release-level security validation | J85: Jawahar | K85: Platform | L85: High | M85: Not Started | N85: 46508 | O85: 46514 | P85: =IF(OR(N85="",O85=""),"",O85-N85+1) | Q85: 0 | R85: 40 | S85: 0 | T85: =S85-R85 | U85: 4400 | V85: T-080 | Y85: Confirm kickoff & acceptance criteria | Z85: R27.Q2 | AA85: Include=Yes | Source=FY27 V1 | Timeline=Q4 FY27 | AB85: No
A86: T-082 | B86: CS 2.0 Core — Tech Maintenance | C86: CS 2.0 Core | D86: Tech Maintenance | E86: Sprint 21 | F86: Hypercare | G86: Reliability | H86: Release Management, Regression Testing and Test Automation | I86: Release Management Activities - Regression Testing & Automation - Manage release activities, coordinate deployments, perform regression testing, maintain automation scripts, validate fixes, support release sign-off, and monitor post-release stability. This includes improving regression automation coverage to reduce manual effort and improve release quality. Note: Reduced this effort considering the release maangement will also go to the respective features, for the delivery customization this will be part of the delivery budget | J86: Jawahar | K86: Platform | L86: Critical | M86: Not Started | N86: 46503 | O86: 46527 | P86: =IF(OR(N86="",O86=""),"",O86-N86+1) | Q86: 0 | R86: 150 | S86: 0 | T86: =S86-R86 | U86: 16500 | V86: T-081 | Y86: Confirm kickoff & acceptance criteria | Z86: R27.Q2 | AA86: Include=Yes | Source=FY27 V1 | Timeline=Q4 FY27 | AB86: No
A87: T-083 | B87: CS 2.0 Core — Tech Maintenance | C87: CS 2.0 Core | D87: Tech Maintenance | E87: Sprint 22 | F87: Hypercare | G87: Reliability | H87: Performance Testing, Tuning and Test Suite Management | I87: Perform performance testing as per the planned test schedule, followed by performance fine-tuning, regression testing, test suite maintenance, fixture updates, and automation improvements. This includes adding or removing test fixtures, maintaining test scripts, validating performance improvements, and ensuring the test suite remains aligned with application changes. Note: Reduced this effort considering the release maangement will also go to the respective features | J87: Jawahar | K87: Platform | L87: High | M87: Not Started | N87: 46519 | O87: 46543 | P87: =IF(OR(N87="",O87=""),"",O87-N87+1) | Q87: 0 | R87: 150 | S87: 0 | T87: =S87-R87 | U87: 16500 | V87: T-082 | Y87: Confirm kickoff & acceptance criteria | Z87: R27.Q2 | AA87: Include=Yes | Source=FY27 V1 | Timeline=Q4 FY27 | AB87: No
A88: T-084 | B88: CS 2.0 Core — Tech Maintenance | C88: CS 2.0 Core | D88: Tech Maintenance | E88: Sprint 23 | F88: Hypercare | G88: Reliability | H88: DevOps Management, Improvements and Pipeline Monitoring | I88: Devops Management/Improvement/Monitoring - Manage and improve the existing DevOps setup by enhancing CI/CD pipelines, adding new deployment workflows, optimizing automation, monitoring pipeline health, troubleshooting deployment issues, and supporting DevOps changes required for new services, environments, and platform upgrades. | J88: Jawahar | K88: Platform | L88: Critical | M88: Not Started | N88: 46526 | O88: 46531 | P88: =IF(OR(N88="",O88=""),"",O88-N88+1) | Q88: 0 | R88: 36 | S88: 0 | T88: =S88-R88 | U88: 3960 | V88: T-083 | X88: R-14 | Y88: Confirm kickoff & acceptance criteria | Z88: R27.Q2 | AA88: Include=Yes | Source=FY27 V1 | Timeline=Q4 FY27 | AB88: No
A89: T-085 | B89: CS 2.0 Core — Tech Maintenance | C89: CS 2.0 Core | D89: Tech Maintenance | E89: Sprint 24 | F89: Hypercare | G89: Reliability | H89: Release Based Feature Documentation | I89: Create release based feature documentation covering new features, functional changes, configuration steps, usage flows, dependencies, screenshots, and known limitations. This will support delivery, QA, support, product, and implementation teams in understanding and adopting each release | J89: Jawahar | K89: Platform | L89: Critical | M89: Not Started | N89: 46538 | O89: 46543 | P89: =IF(OR(N89="",O89=""),"",O89-N89+1) | Q89: 0 | R89: 36 | S89: 0 | T89: =S89-R89 | U89: 3960 | V89: T-084 | Y89: Confirm kickoff & acceptance criteria | Z89: R27.Q2 | AA89: Include=Yes | Source=FY27 V1 | Timeline=Q4 FY27 | AB89: No
A90: T-086 | B90: CS 2.0 Core — Tech Maintenance | C90: CS 2.0 Core | D90: Tech Maintenance | E90: Sprint 19 | F90: Hypercare | G90: Reliability | H90: Monthly Library Upgrade Assessment and Remediation Across Services | I90: Perform monthly scheduled library and package upgrade assessment across 20+ services, including web apps, Node.js services, workers, and .NET services. This includes identifying available upgrades, assessing security and compatibility impact, handling breaking changes, applying required fixes, validating builds, and supporting regression/release readiness. | J90: Jawahar | K90: Platform | L90: Critical | M90: Not Started | N90: 46521 | O90: 46525 | P90: =IF(OR(N90="",O90=""),"",O90-N90+1) | Q90: 0 | R90: 30 | S90: 0 | T90: =S90-R90 | U90: 3300 | V90: T-085 | Y90: Confirm kickoff & acceptance criteria | Z90: R27.Q2 | AA90: Include=Yes | Source=FY27 V1 | Timeline=Q4 FY27 | AB90: No
A91: T-087 | B91: CS 2.0 Core — Tech Maintenance | C91: CS 2.0 Core | D91: Tech Maintenance | E91: Sprint 20 | F91: Hypercare | G91: Reliability | H91: Cloud Usage Chargeback Model, Monthly Tenant-Level Allocation | I91: Cloud Usage Charge back model (Monthly) - Prepare monthly tenant-level cloud usage chargeback by collecting cloud consumption data, applying agreed allocation rules, validating usage/cost anomalies, and publishing the monthly chargeback summary for each tenant. | J91: Jawahar | K91: Platform | L91: Critical | M91: Not Started | N91: 46486 | O91: 46490 | P91: =IF(OR(N91="",O91=""),"",O91-N91+1) | Q91: 0 | R91: 12 | S91: 0 | T91: =S91-R91 | U91: 1320 | V91: T-086 | Y91: Confirm kickoff & acceptance criteria | Z91: R27.Q2 | AA91: Include=Yes | Source=FY27 V1 | Timeline=Q4 FY27 | AB91: No
A92: T-088 | B92: CS 2.0 Data — PIS New Feature | C92: CS 2.0 Data | D92: PIS New Feature | E92: Sprint 03 | F92: Build | G92: Data | H92: Insight Agent Requirements Building and POC Closure | J92: Siva | K92: Data & AI | L92: High | M92: Not Started | N92: 46235 | O92: 46251 | P92: =IF(OR(N92="",O92=""),"",O92-N92+1) | Q92: 0 | R92: 100 | S92: 0 | T92: =S92-R92 | U92: 11000 | Y92: Confirm kickoff & acceptance criteria | Z92: R26.Q1 | AA92: Include=Yes | Source=FY27 V1 | Timeline=Q1 FY27 | AB92: No
A93: T-089 | B93: CS 2.0 Data — PIS New Feature | C93: CS 2.0 Data | D93: PIS New Feature | E93: Sprint 04 | F93: Build | G93: Data | H93: Insights Agent | I93: Phase 1 - ANSWER & GUIDE | J93: Siva | K93: Data & AI | L93: High | M93: Not Started | N93: 46241 | O93: 46273 | P93: =IF(OR(N93="",O93=""),"",O93-N93+1) | Q93: 0 | R93: 200 | S93: 0 | T93: =S93-R93 | U93: 22000 | V93: T-088 | Y93: Confirm kickoff & acceptance criteria | Z93: R26.Q1 | AA93: Include=Yes | Source=FY27 V1 | Timeline=Q1 FY27 | AB93: No
A94: T-090 | B94: CS 2.0 Data — PIS New Feature | C94: CS 2.0 Data | D94: PIS New Feature | E94: Sprint 05 | F94: Build | G94: Data | H94: Insights Agent | I94: Phase 2 - EXPLAIN & DIAGNOSE | J94: Siva | K94: Data & AI | L94: High | M94: In Progress | N94: 46259 | O94: 46291 | P94: =IF(OR(N94="",O94=""),"",O94-N94+1) | Q94: 0.35 | R94: 200 | S94: 72.8 | T94: =S94-R94 | U94: 22000 | V94: T-089 | Y94: Continue sprint commitments; demos Friday | Z94: R26.Q1 | AA94: Include=Yes | Source=FY27 V1 | Timeline=Q1 FY27 | AB94: No
A95: T-091 | B95: CS 2.0 Data — PIS New Feature | C95: CS 2.0 Data | D95: PIS New Feature | E95: Sprint 06 | F95: Build | G95: Data | H95: Insights Agent | I95: Phase 3 - PREDICT & OPTIMISE | J95: Siva | K95: Data & AI | L95: High | M95: Not Started | N95: 46207 | O95: 46239 | P95: =IF(OR(N95="",O95=""),"",O95-N95+1) | Q95: 0 | R95: 200 | S95: 0 | T95: =S95-R95 | U95: 22000 | V95: T-090 | Y95: Confirm kickoff & acceptance criteria | Z95: R26.Q1 | AA95: Include=Yes | Source=FY27 V1 | Timeline=Q1 FY27 | AB95: No
A96: T-092 | B96: CS 2.0 Data — PIS New Feature | C96: CS 2.0 Data | D96: PIS New Feature | E96: Sprint 07 | F96: Build | G96: Data | H96: Insights Agent | I96: Phase 1 - ANSWER & GUIDE | J96: Siva | K96: Data & AI | L96: High | M96: Not Started | N96: 46327 | O96: 46359 | P96: =IF(OR(N96="",O96=""),"",O96-N96+1) | Q96: 0 | R96: 200 | S96: 0 | T96: =S96-R96 | U96: 22000 | V96: T-091 | Y96: Confirm kickoff & acceptance criteria | Z96: R26.Q2 | AA96: Include=Yes | Source=FY27 V1 | Timeline=Q2 FY27 | AB96: No
A97: T-093 | B97: CS 2.0 Data — PIS New Feature | C97: CS 2.0 Data | D97: PIS New Feature | E97: Sprint 08 | F97: Build | G97: Data | H97: Insights Agent | I97: Phase 2 - EXPLAIN & DIAGNOSE | J97: Siva | K97: Data & AI | L97: High | M97: Not Started | N97: 46330 | O97: 46362 | P97: =IF(OR(N97="",O97=""),"",O97-N97+1) | Q97: 0 | R97: 200 | S97: 0 | T97: =S97-R97 | U97: 22000 | V97: T-092 | Y97: Confirm kickoff & acceptance criteria | Z97: R26.Q2 | AA97: Include=Yes | Source=FY27 V1 | Timeline=Q2 FY27 | AB97: No
A98: T-094 | B98: CS 2.0 Data — PIS New Feature | C98: CS 2.0 Data | D98: PIS New Feature | E98: Sprint 09 | F98: Build | G98: Data | H98: Insights Agent | I98: Phase 3 - PREDICT & OPTIMISE | J98: Siva | K98: Data & AI | L98: High | M98: Not Started | N98: 46301 | O98: 46333 | P98: =IF(OR(N98="",O98=""),"",O98-N98+1) | Q98: 0 | R98: 200 | S98: 0 | T98: =S98-R98 | U98: 22000 | V98: T-093 | Y98: Confirm kickoff & acceptance criteria | Z98: R26.Q2 | AA98: Include=Yes | Source=FY27 V1 | Timeline=Q2 FY27 | AB98: No
A99: T-095 | B99: CS 2.0 Data — PIS New Feature | C99: CS 2.0 Data | D99: PIS New Feature | E99: Sprint 10 | F99: Build | G99: Data | H99: Journey Builder - Requirements Building | I99: Journey Builder Requirements. Build the work package, Design and estimate based on the work package | J99: Siva | K99: Data & AI | L99: High | M99: Not Started | N99: 46353 | O99: 46369 | P99: =IF(OR(N99="",O99=""),"",O99-N99+1) | Q99: 0 | R99: 100 | S99: 0 | T99: =S99-R99 | U99: 11000 | V99: T-094 | Y99: Confirm kickoff & acceptance criteria | Z99: R26.Q2 | AA99: Include=Yes | Source=FY27 V1 | Timeline=Q2 FY27 | AB99: No
A100: T-096 | B100: CS 2.0 Data — PIS New Feature | C100: CS 2.0 Data | D100: PIS New Feature | E100: Sprint 11 | F100: Build | G100: Data | H100: Journey Builder | I100: Phase 1 - ORCHESTRATE - Build the Engine Low-code journey canvas with drag-and-drop trigger, wait, and condition logic. Automated actions across communication, incentives, and learning interventions. Omni-channel response tracking with automated follow-up sequencing. Extend journeys with Agent Node that invoke specialised AI agents for contextual decisioning and message personalization. | J100: Siva | K100: Data & AI | L100: High | M100: Not Started | N100: 46302 | O100: 46334 | P100: =IF(OR(N100="",O100=""),"",O100-N100+1) | Q100: 0 | R100: 200 | S100: 0 | T100: =S100-R100 | U100: 22000 | V100: T-095 | Y100: Confirm kickoff & acceptance criteria | Z100: R26.Q2 | AA100: Include=Yes | Source=FY27 V1 | Timeline=Q2 FY27 | AB100: No
A101: T-097 | B101: CS 2.0 Data — PIS New Feature | C101: CS 2.0 Data | D101: PIS New Feature | E101: Sprint 12 | F101: Build | G101: Data | H101: Journey Builder | I101: Phase 2 - GUIDE with Recommendations Journey Builder framework powers Earn Advisor to continuously guide partners towards the highest-value earning actions. A Next-Best-Action Agent evaluates partner context across sales patterns, behaviours and program participation signals. Identifies and ranks high-value opportunities - including product mix gaps, cross-sell opportunities and time-sensitive incentives. Agent presents prioritised actions back to Journey Builder to enable contextual interventions. | J101: Siva | K101: Data & AI | L101: High | M101: Not Started | N101: 46338 | O101: 46370 | P101: =IF(OR(N101="",O101=""),"",O101-N101+1) | Q101: 0 | R101: 200 | S101: 0 | T101: =S101-R101 | U101: 22000 | V101: T-096 | Y101: Confirm kickoff & acceptance criteria | Z101: R26.Q2 | AA101: Include=Yes | Source=FY27 V1 | Timeline=Q2 FY27 | AB101: No
A102: T-098 | B102: CS 2.0 Data — PIS New Feature | C102: CS 2.0 Data | D102: PIS New Feature | E102: Sprint 07 | F102: Build | G102: Data | H102: Journey Builder | I102: Phase 3 - PREDICT with Intelligence Build prediction agents that continuously analyse participant context across partner performance, behaviours and engagement patterns. Generate explainable outcome predictions - such as churn risk, activation likelihood, target shortfalls and tier progression risk. Return prediction confidence, key drivers & recommended interventions rather than standalone scores. Present predicted outcomes to Journey Builder to enable contextual interventions. | J102: Siva | K102: Data & AI | L102: High | M102: Not Started | N102: 46343 | O102: 46375 | P102: =IF(OR(N102="",O102=""),"",O102-N102+1) | Q102: 0 | R102: 200 | S102: 0 | T102: =S102-R102 | U102: 22000 | V102: T-097 | Y102: Confirm kickoff & acceptance criteria | Z102: R26.Q2 | AA102: Include=Yes | Source=FY27 V1 | Timeline=Q2 FY27 | AB102: No
A103: T-099 | B103: CS 2.0 Data — PIS New Feature | C103: CS 2.0 Data | D103: PIS New Feature | E103: Sprint 15 | F103: Build | G103: Data | H103: Journey Builder | I103: Phase 1 - ORCHESTRATE - Build the Engine Low-code journey canvas with drag-and-drop trigger, wait, and condition logic. Automated actions across communication, incentives, and learning interventions. Omni-channel response tracking with automated follow-up sequencing. Extend journeys with Agent Node that invoke specialised AI agents for contextual decisioning and message personalization. | J103: Siva | K103: Data & AI | L103: High | M103: Not Started | N103: 46396 | O103: 46428 | P103: =IF(OR(N103="",O103=""),"",O103-N103+1) | Q103: 0 | R103: 200 | S103: 0 | T103: =S103-R103 | U103: 22000 | V103: T-098 | Y103: Confirm kickoff & acceptance criteria | Z103: R27.Q1 | AA103: Include=Yes | Source=FY27 V1 | Timeline=Q3 FY27 | AB103: No
...

Sheet Gantt Chart
A1: GANTT CHART — FY27 (Weekly / Monthly / Quarterly)
A2: Bars auto-highlight from Start/End. Legend: Green=Completed · Blue=In Progress · Yellow=At Risk · Red=Blocked/Critical · Grey=Not Started · ◆=Milestone week · Orange header=Current week
I3: =IF(AND(TODAY()>=I$4,TODAY()<I$4+7),"▶","") | J3: =IF(AND(TODAY()>=J$4,TODAY()<J$4+7),"▶","") | K3: =IF(AND(TODAY()>=K$4,TODAY()<K$4+7),"▶","") | L3: =IF(AND(TODAY()>=L$4,TODAY()<L$4+7),"▶","") | M3: =IF(AND(TODAY()>=M$4,TODAY()<M$4+7),"▶","") | N3: =IF(AND(TODAY()>=N$4,TODAY()<N$4+7),"▶","") | O3: =IF(AND(TODAY()>=O$4,TODAY()<O$4+7),"▶","") | P3: =IF(AND(TODAY()>=P$4,TODAY()<P$4+7),"▶","") | ... BI3: =IF(AND(TODAY()>=BI$4,TODAY()<BI$4+7),"▶","")
A4: Task ID | B4: Task Name | C4: Owner | D4: Status | E4: Start | F4: End | G4: % Complete | H4: Critical | I4: 46202 | J4: 46209 | K4: 46216 | L4: 46223 | M4: 46230 | N4: 46237 | O4: 46244 | P4: 46251 | Q4: 46258 | R4: 46265 | S4: 46272 | T4: 46279 | U4: 46286 | V4: 46293 | W4: 46300 | X4: 46307 | Y4: 46314 | Z4: 46321 | AA4: 46328 | AB4: 46335 | AC4: 46342 | AD4: 46349 | AE4: 46356 | AF4: 46363 | AG4: 46370 | AH4: 46377 | AI4: 46384 | AJ4: 46391 | AK4: 46398 | AL4: 46405 | AM4: 46412 | AN4: 46419 | AO4: 46426 | AP4: 46433 | AQ4: 46440 | AR4: 46447 | AS4: 46454 | AT4: 46461 | AU4: 46468 | AV4: 46475 | AW4: 46482 | AX4: 46489 | AY4: 46496 | AZ4: 46503 | BA4: 46510 | BB4: 46517 | BC4: 46524 | BD4: 46531 | BE4: 46538 | BF4: 46545 | BG4: 46552 | BH4: 46559 | BI4: 46566
A5: T-001 | B5: Shutting down BRIKS service from Nackle | C5: MJ | D5: At Risk | E5: 46287 | F5: 46293 | G5: 0.13 | H5: No | I5: =IF(OR($E5="",$F5=""),"",IF(AND(I$4<=$F5,I$4+6>=$E5),IF($F5-$E5<=2,"◆",IF($H5="Yes","X",LEFT($D5,1))),"")) | J5: =IF(OR($E5="",$F5=""),"",IF(AND(J$4<=$F5,J$4+6>=$E5),IF($F5-$E5<=2,"◆",IF($H5="Yes","X",LEFT($D5,1))),"")) | K5: =IF(OR($E5="",$F5=""),"",IF(AND(K$4<=$F5,K$4+6>=$E5),IF($F5-$E5<=2,"◆",IF($H5="Yes","X",LEFT($D5,1))),"")) | L5: =IF(OR($E5="",$F5=""),"",IF(AND(L$4<=$F5,L$4+6>=$E5),IF($F5-$E5<=2,"◆",IF($H5="Yes","X",LEFT($D5,1))),"")) | M5: =IF(OR($E5="",$F5=""),"",IF(AND(M$4<=$F5,M$4+6>=$E5),IF($F5-$E5<=2,"◆",IF($H5="Yes","X",LEFT($D5,1))),"")) | N5: =IF(OR($E5="",$F5=""),"",IF(AND(N$4<=$F5,N$4+6>=$E5),IF($F5-$E5<=2,"◆",IF($H5="Yes","X",LEFT($D5,1))),"")) | O5: =IF(OR($E5="",$F5=""),"",IF(AND(O$4<=$F5,O$4+6>=$E5),IF($F5-$E5<=2,"◆",IF($H5="Yes","X",LEFT($D5,1))),"")) | P5: =IF(OR($E5="",$F5=""),"",IF(AND(P$4<=$F5,P$4+6>=$E5),IF($F5-$E5<=2,"◆",IF($H5="Yes","X",LEFT($D5,1))),"")) | ... BI5: =IF(OR($E5="",$F5=""),"",IF(AND(BI$4<=$F5,BI$4+6>=$E5),IF($F5-$E5<=2,"◆",IF($H5="Yes","X",LEFT($D5,1))),""))
A6: T-002 | B6: Shutting Down Coupon/OTP Services | C6: MJ | D6: In Progress | E6: 46213 | F6: 46226 | G6: 0.36 | H6: No | I6: =IF(OR($E6="",$F6=""),"",IF(AND(I$4<=$F6,I$4+6>=$E6),IF($F6-$E6<=2,"◆",IF($H6="Yes","X",LEFT($D6,1))),"")) | J6: =IF(OR($E6="",$F6=""),"",IF(AND(J$4<=$F6,J$4+6>=$E6),IF($F6-$E6<=2,"◆",IF($H6="Yes","X",LEFT($D6,1))),"")) | K6: =IF(OR($E6="",$F6=""),"",IF(AND(K$4<=$F6,K$4+6>=$E6),IF($F6-$E6<=2,"◆",IF($H6="Yes","X",LEFT($D6,1))),"")) | L6: =IF(OR($E6="",$F6=""),"",IF(AND(L$4<=$F6,L$4+6>=$E6),IF($F6-$E6<=2,"◆",IF($H6="Yes","X",LEFT($D6,1))),"")) | M6: =IF(OR($E6="",$F6=""),"",IF(AND(M$4<=$F6,M$4+6>=$E6),IF($F6-$E6<=2,"◆",IF($H6="Yes","X",LEFT($D6,1))),"")) | N6: =IF(OR($E6="",$F6=""),"",IF(AND(N$4<=$F6,N$4+6>=$E6),IF($F6-$E6<=2,"◆",IF($H6="Yes","X",LEFT($D6,1))),"")) | O6: =IF(OR($E6="",$F6=""),"",IF(AND(O$4<=$F6,O$4+6>=$E6),IF($F6-$E6<=2,"◆",IF($H6="Yes","X",LEFT($D6,1))),"")) | P6: =IF(OR($E6="",$F6=""),"",IF(AND(P$4<=$F6,P$4+6>=$E6),IF($F6-$E6<=2,"◆",IF($H6="Yes","X",LEFT($D6,1))),"")) | ... BI6: =IF(OR($E6="",$F6=""),"",IF(AND(BI$4<=$F6,BI$4+6>=$E6),IF($F6-$E6<=2,"◆",IF($H6="Yes","X",LEFT($D6,1))),""))
A7: T-003 | B7: Integrate the email validation service for Channel Smart 1.0(Roshni to check) | C7: MJ | D7: In Progress | E7: 46236 | F7: 46242 | G7: 0.36 | H7: No | I7: =IF(OR($E7="",$F7=""),"",IF(AND(I$4<=$F7,I$4+6>=$E7),IF($F7-$E7<=2,"◆",IF($H7="Yes","X",LEFT($D7,1))),"")) | J7: =IF(OR($E7="",$F7=""),"",IF(AND(J$4<=$F7,J$4+6>=$E7),IF($F7-$E7<=2,"◆",IF($H7="Yes","X",LEFT($D7,1))),"")) | K7: =IF(OR($E7="",$F7=""),"",IF(AND(K$4<=$F7,K$4+6>=$E7),IF($F7-$E7<=2,"◆",IF($H7="Yes","X",LEFT($D7,1))),"")) | L7: =IF(OR($E7="",$F7=""),"",IF(AND(L$4<=$F7,L$4+6>=$E7),IF($F7-$E7<=2,"◆",IF($H7="Yes","X",LEFT($D7,1))),"")) | M7: =IF(OR($E7="",$F7=""),"",IF(AND(M$4<=$F7,M$4+6>=$E7),IF($F7-$E7<=2,"◆",IF($H7="Yes","X",LEFT($D7,1))),"")) | N7: =IF(OR($E7="",$F7=""),"",IF(AND(N$4<=$F7,N$4+6>=$E7),IF($F7-$E7<=2,"◆",IF($H7="Yes","X",LEFT($D7,1))),"")) | O7: =IF(OR($E7="",$F7=""),"",IF(AND(O$4<=$F7,O$4+6>=$E7),IF($F7-$E7<=2,"◆",IF($H7="Yes","X",LEFT($D7,1))),"")) | P7: =IF(OR($E7="",$F7=""),"",IF(AND(P$4<=$F7,P$4+6>=$E7),IF($F7-$E7<=2,"◆",IF($H7="Yes","X",LEFT($D7,1))),"")) | ... BI7: =IF(OR($E7="",$F7=""),"",IF(AND(BI$4<=$F7,BI$4+6>=$E7),IF($F7-$E7<=2,"◆",IF($H7="Yes","X",LEFT($D7,1))),""))
A8: T-004 | B8: Build Unsubscribe feature for all the promotional emails(Roshni to check) | C8: MJ | D8: Not Started | E8: 46235 | F8: 46244 | G8: 0 | H8: No | I8: =IF(OR($E8="",$F8=""),"",IF(AND(I$4<=$F8,I$4+6>=$E8),IF($F8-$E8<=2,"◆",IF($H8="Yes","X",LEFT($D8,1))),"")) | J8: =IF(OR($E8="",$F8=""),"",IF(AND(J$4<=$F8,J$4+6>=$E8),IF($F8-$E8<=2,"◆",IF($H8="Yes","X",LEFT($D8,1))),"")) | K8: =IF(OR($E8="",$F8=""),"",IF(AND(K$4<=$F8,K$4+6>=$E8),IF($F8-$E8<=2,"◆",IF($H8="Yes","X",LEFT($D8,1))),"")) | L8: =IF(OR($E8="",$F8=""),"",IF(AND(L$4<=$F8,L$4+6>=$E8),IF($F8-$E8<=2,"◆",IF($H8="Yes","X",LEFT($D8,1))),"")) | M8: =IF(OR($E8="",$F8=""),"",IF(AND(M$4<=$F8,M$4+6>=$E8),IF($F8-$E8<=2,"◆",IF($H8="Yes","X",LEFT($D8,1))),"")) | N8: =IF(OR($E8="",$F8=""),"",IF(AND(N$4<=$F8,N$4+6>=$E8),IF($F8-$E8<=2,"◆",IF($H8="Yes","X",LEFT($D8,1))),"")) | O8: =IF(OR($E8="",$F8=""),"",IF(AND(O$4<=$F8,O$4+6>=$E8),IF($F8-$E8<=2,"◆",IF($H8="Yes","X",LEFT($D8,1))),"")) | P8: =IF(OR($E8="",$F8=""),"",IF(AND(P$4<=$F8,P$4+6>=$E8),IF($F8-$E8<=2,"◆",IF($H8="Yes","X",LEFT($D8,1))),"")) | ... BI8: =IF(OR($E8="",$F8=""),"",IF(AND(BI$4<=$F8,BI$4+6>=$E8),IF($F8-$E8<=2,"◆",IF($H8="Yes","X",LEFT($D8,1))),""))
A9: T-005 | B9: Cash + Wallet + Compliance - Integration patch for CS 1.0 | C9: MJ | D9: Not Started | E9: 46235 | F9: 46267 | G9: 0 | H9: No | I9: =IF(OR($E9="",$F9=""),"",IF(AND(I$4<=$F9,I$4+6>=$E9),IF($F9-$E9<=2,"◆",IF($H9="Yes","X",LEFT($D9,1))),"")) | J9: =IF(OR($E9="",$F9=""),"",IF(AND(J$4<=$F9,J$4+6>=$E9),IF($F9-$E9<=2,"◆",IF($H9="Yes","X",LEFT($D9,1))),"")) | K9: =IF(OR($E9="",$F9=""),"",IF(AND(K$4<=$F9,K$4+6>=$E9),IF($F9-$E9<=2,"◆",IF($H9="Yes","X",LEFT($D9,1))),"")) | L9: =IF(OR($E9="",$F9=""),"",IF(AND(L$4<=$F9,L$4+6>=$E9),IF($F9-$E9<=2,"◆",IF($H9="Yes","X",LEFT($D9,1))),"")) | M9: =IF(OR($E9="",$F9=""),"",IF(AND(M$4<=$F9,M$4+6>=$E9),IF($F9-$E9<=2,"◆",IF($H9="Yes","X",LEFT($D9,1))),"")) | N9: =IF(OR($E9="",$F9=""),"",IF(AND(N$4<=$F9,N$4+6>=$E9),IF($F9-$E9<=2,"◆",IF($H9="Yes","X",LEFT($D9,1))),"")) | O9: =IF(OR($E9="",$F9=""),"",IF(AND(O$4<=$F9,O$4+6>=$E9),IF($F9-$E9<=2,"◆",IF($H9="Yes","X",LEFT($D9,1))),"")) | P9: =IF(OR($E9="",$F9=""),"",IF(AND(P$4<=$F9,P$4+6>=$E9),IF($F9-$E9<=2,"◆",IF($H9="Yes","X",LEFT($D9,1))),"")) | ... BI9: =IF(OR($E9="",$F9=""),"",IF(AND(BI$4<=$F9,BI$4+6>=$E9),IF($F9-$E9<=2,"◆",IF($H9="Yes","X",LEFT($D9,1))),""))
A10: T-006 | B10: Build Pipeline for Achievo to be updated | C10: MJ | D10: Not Started | E10: 46282 | F10: 46291 | G10: 0 | H10: No | I10: =IF(OR($E10="",$F10=""),"",IF(AND(I$4<=$F10,I$4+6>=$E10),IF($F10-$E10<=2,"◆",IF($H10="Yes","X",LEFT($D10,1))),"")) | J10: =IF(OR($E10="",$F10=""),"",IF(AND(J$4<=$F10,J$4+6>=$E10),IF($F10-$E10<=2,"◆",IF($H10="Yes","X",LEFT($D10,1))),"")) | K10: =IF(OR($E10="",$F10=""),"",IF(AND(K$4<=$F10,K$4+6>=$E10),IF($F10-$E10<=2,"◆",IF($H10="Yes","X",LEFT($D10,1))),"")) | L10: =IF(OR($E10="",$F10=""),"",IF(AND(L$4<=$F10,L$4+6>=$E10),IF($F10-$E10<=2,"◆",IF($H10="Yes","X",LEFT($D10,1))),"")) | M10: =IF(OR($E10="",$F10=""),"",IF(AND(M$4<=$F10,M$4+6>=$E10),IF($F10-$E10<=2,"◆",IF($H10="Yes","X",LEFT($D10,1))),"")) | N10: =IF(OR($E10="",$F10=""),"",IF(AND(N$4<=$F10,N$4+6>=$E10),IF($F10-$E10<=2,"◆",IF($H10="Yes","X",LEFT($D10,1))),"")) | O10: =IF(OR($E10="",$F10=""),"",IF(AND(O$4<=$F10,O$4+6>=$E10),IF($F10-$E10<=2,"◆",IF($H10="Yes","X",LEFT($D10,1))),"")) | P10: =IF(OR($E10="",$F10=""),"",IF(AND(P$4<=$F10,P$4+6>=$E10),IF($F10-$E10<=2,"◆",IF($H10="Yes","X",LEFT($D10,1))),"")) | ... BI10: =IF(OR($E10="",$F10=""),"",IF(AND(BI$4<=$F10,BI$4+6>=$E10),IF($F10-$E10<=2,"◆",IF($H10="Yes","X",LEFT($D10,1))),""))
A11: T-007 | B11: Integrate the email validation service for Channel Smart 2.0(Roshni to check) | C11: MJ | D11: Not Started | E11: 46257 | F11: 46263 | G11: 0 | H11: No | I11: =IF(OR($E11="",$F11=""),"",IF(AND(I$4<=$F11,I$4+6>=$E11),IF($F11-$E11<=2,"◆",IF($H11="Yes","X",LEFT($D11,1))),"")) | J11: =IF(OR($E11="",$F11=""),"",IF(AND(J$4<=$F11,J$4+6>=$E11),IF($F11-$E11<=2,"◆",IF($H11="Yes","X",LEFT($D11,1))),"")) | K11: =IF(OR($E11="",$F11=""),"",IF(AND(K$4<=$F11,K$4+6>=$E11),IF($F11-$E11<=2,"◆",IF($H11="Yes","X",LEFT($D11,1))),"")) | L11: =IF(OR($E11="",$F11=""),"",IF(AND(L$4<=$F11,L$4+6>=$E11),IF($F11-$E11<=2,"◆",IF($H11="Yes","X",LEFT($D11,1))),"")) | M11: =IF(OR($E11="",$F11=""),"",IF(AND(M$4<=$F11,M$4+6>=$E11),IF($F11-$E11<=2,"◆",IF($H11="Yes","X",LEFT($D11,1))),"")) | N11: =IF(OR($E11="",$F11=""),"",IF(AND(N$4<=$F11,N$4+6>=$E11),IF($F11-$E11<=2,"◆",IF($H11="Yes","X",LEFT($D11,1))),"")) | O11: =IF(OR($E11="",$F11=""),"",IF(AND(O$4<=$F11,O$4+6>=$E11),IF($F11-$E11<=2,"◆",IF($H11="Yes","X",LEFT($D11,1))),"")) | P11: =IF(OR($E11="",$F11=""),"",IF(AND(P$4<=$F11,P$4+6>=$E11),IF($F11-$E11<=2,"◆",IF($H11="Yes","X",LEFT($D11,1))),"")) | ... BI11: =IF(OR($E11="",$F11=""),"",IF(AND(BI$4<=$F11,BI$4+6>=$E11),IF($F11-$E11<=2,"◆",IF($H11="Yes","X",LEFT($D11,1))),""))
A12: T-008 | B12: Build Unsubscribe feature for all the promotional emails(Roshni to check) | C12: MJ | D12: Not Started | E12: 46260 | F12: 46269 | G12: 0 | H12: No | I12: =IF(OR($E12="",$F12=""),"",IF(AND(I$4<=$F12,I$4+6>=$E12),IF($F12-$E12<=2,"◆",IF($H12="Yes","X",LEFT($D12,1))),"")) | J12: =IF(OR($E12="",$F12=""),"",IF(AND(J$4<=$F12,J$4+6>=$E12),IF($F12-$E12<=2,"◆",IF($H12="Yes","X",LEFT($D12,1))),"")) | K12: =IF(OR($E12="",$F12=""),"",IF(AND(K$4<=$F12,K$4+6>=$E12),IF($F12-$E12<=2,"◆",IF($H12="Yes","X",LEFT($D12,1))),"")) | L12: =IF(OR($E12="",$F12=""),"",IF(AND(L$4<=$F12,L$4+6>=$E12),IF($F12-$E12<=2,"◆",IF($H12="Yes","X",LEFT($D12,1))),"")) | M12: =IF(OR($E12="",$F12=""),"",IF(AND(M$4<=$F12,M$4+6>=$E12),IF($F12-$E12<=2,"◆",IF($H12="Yes","X",LEFT($D12,1))),"")) | N12: =IF(OR($E12="",$F12=""),"",IF(AND(N$4<=$F12,N$4+6>=$E12),IF($F12-$E12<=2,"◆",IF($H12="Yes","X",LEFT($D12,1))),"")) | O12: =IF(OR($E12="",$F12=""),"",IF(AND(O$4<=$F12,O$4+6>=$E12),IF($F12-$E12<=2,"◆",IF($H12="Yes","X",LEFT($D12,1))),"")) | P12: =IF(OR($E12="",$F12=""),"",IF(AND(P$4<=$F12,P$4+6>=$E12),IF($F12-$E12<=2,"◆",IF($H12="Yes","X",LEFT($D12,1))),"")) | ... BI12: =IF(OR($E12="",$F12=""),"",IF(AND(BI$4<=$F12,BI$4+6>=$E12),IF($F12-$E12<=2,"◆",IF($H12="Yes","X",LEFT($D12,1))),""))
A13: T-009 | B13: ERP Connerctor Service(Saleforce) | C13: MJ | D13: Not Started | E13: 46204 | F13: 46261 | G13: 0 | H13: No | I13: =IF(OR($E13="",$F13=""),"",IF(AND(I$4<=$F13,I$4+6>=$E13),IF($F13-$E13<=2,"◆",IF($H13="Yes","X",LEFT($D13,1))),"")) | J13: =IF(OR($E13="",$F13=""),"",IF(AND(J$4<=$F13,J$4+6>=$E13),IF($F13-$E13<=2,"◆",IF($H13="Yes","X",LEFT($D13,1))),"")) | K13: =IF(OR($E13="",$F13=""),"",IF(AND(K$4<=$F13,K$4+6>=$E13),IF($F13-$E13<=2,"◆",IF($H13="Yes","X",LEFT($D13,1))),"")) | L13: =IF(OR($E13="",$F13=""),"",IF(AND(L$4<=$F13,L$4+6>=$E13),IF($F13-$E13<=2,"◆",IF($H13="Yes","X",LEFT($D13,1))),"")) | M13: =IF(OR($E13="",$F13=""),"",IF(AND(M$4<=$F13,M$4+6>=$E13),IF($F13-$E13<=2,"◆",IF($H13="Yes","X",LEFT($D13,1))),"")) | N13: =IF(OR($E13="",$F13=""),"",IF(AND(N$4<=$F13,N$4+6>=$E13),IF($F13-$E13<=2,"◆",IF($H13="Yes","X",LEFT($D13,1))),"")) | O13: =IF(OR($E13="",$F13=""),"",IF(AND(O$4<=$F13,O$4+6>=$E13),IF($F13-$E13<=2,"◆",IF($H13="Yes","X",LEFT($D13,1))),"")) | P13: =IF(OR($E13="",$F13=""),"",IF(AND(P$4<=$F13,P$4+6>=$E13),IF($F13-$E13<=2,"◆",IF($H13="Yes","X",LEFT($D13,1))),"")) | ... BI13: =IF(OR($E13="",$F13=""),"",IF(AND(BI$4<=$F13,BI$4+6>=$E13),IF($F13-$E13<=2,"◆",IF($H13="Yes","X",LEFT($D13,1))),""))
A14: T-010 | B14: Technology refresh | C14: Jawahar | D14: In Progress | E14: 46265 | F14: 46277 | G14: 0.29 | H14: No | I14: =IF(OR($E14="",$F14=""),"",IF(AND(I$4<=$F14,I$4+6>=$E14),IF($F14-$E14<=2,"◆",IF($H14="Yes","X",LEFT($D14,1))),"")) | J14: =IF(OR($E14="",$F14=""),"",IF(AND(J$4<=$F14,J$4+6>=$E14),IF($F14-$E14<=2,"◆",IF($H14="Yes","X",LEFT($D14,1))),"")) | K14: =IF(OR($E14="",$F14=""),"",IF(AND(K$4<=$F14,K$4+6>=$E14),IF($F14-$E14<=2,"◆",IF($H14="Yes","X",LEFT($D14,1))),"")) | L14: =IF(OR($E14="",$F14=""),"",IF(AND(L$4<=$F14,L$4+6>=$E14),IF($F14-$E14<=2,"◆",IF($H14="Yes","X",LEFT($D14,1))),"")) | M14: =IF(OR($E14="",$F14=""),"",IF(AND(M$4<=$F14,M$4+6>=$E14),IF($F14-$E14<=2,"◆",IF($H14="Yes","X",LEFT($D14,1))),"")) | N14: =IF(OR($E14="",$F14=""),"",IF(AND(N$4<=$F14,N$4+6>=$E14),IF($F14-$E14<=2,"◆",IF($H14="Yes","X",LEFT($D14,1))),"")) | O14: =IF(OR($E14="",$F14=""),"",IF(AND(O$4<=$F14,O$4+6>=$E14),IF($F14-$E14<=2,"◆",IF($H14="Yes","X",LEFT($D14,1))),"")) | P14: =IF(OR($E14="",$F14=""),"",IF(AND(P$4<=$F14,P$4+6>=$E14),IF($F14-$E14<=2,"◆",IF($H14="Yes","X",LEFT($D14,1))),"")) | ... BI14: =IF(OR($E14="",$F14=""),"",IF(AND(BI$4<=$F14,BI$4+6>=$E14),IF($F14-$E14<=2,"◆",IF($H14="Yes","X",LEFT($D14,1))),""))
A15: T-011 | B15: Fix for Critical Performance Issue(Claims, File Upload) | C15: Jawahar | D15: In Progress | E15: 46271 | F15: 46284 | G15: 0.22 | H15: No | I15: =IF(OR($E15="",$F15=""),"",IF(AND(I$4<=$F15,I$4+6>=$E15),IF($F15-$E15<=2,"◆",IF($H15="Yes","X",LEFT($D15,1))),"")) | J15: =IF(OR($E15="",$F15=""),"",IF(AND(J$4<=$F15,J$4+6>=$E15),IF($F15-$E15<=2,"◆",IF($H15="Yes","X",LEFT($D15,1))),"")) | K15: =IF(OR($E15="",$F15=""),"",IF(AND(K$4<=$F15,K$4+6>=$E15),IF($F15-$E15<=2,"◆",IF($H15="Yes","X",LEFT($D15,1))),"")) | L15: =IF(OR($E15="",$F15=""),"",IF(AND(L$4<=$F15,L$4+6>=$E15),IF($F15-$E15<=2,"◆",IF($H15="Yes","X",LEFT($D15,1))),"")) | M15: =IF(OR($E15="",$F15=""),"",IF(AND(M$4<=$F15,M$4+6>=$E15),IF($F15-$E15<=2,"◆",IF($H15="Yes","X",LEFT($D15,1))),"")) | N15: =IF(OR($E15="",$F15=""),"",IF(AND(N$4<=$F15,N$4+6>=$E15),IF($F15-$E15<=2,"◆",IF($H15="Yes","X",LEFT($D15,1))),"")) | O15: =IF(OR($E15="",$F15=""),"",IF(AND(O$4<=$F15,O$4+6>=$E15),IF($F15-$E15<=2,"◆",IF($H15="Yes","X",LEFT($D15,1))),"")) | P15: =IF(OR($E15="",$F15=""),"",IF(AND(P$4<=$F15,P$4+6>=$E15),IF($F15-$E15<=2,"◆",IF($H15="Yes","X",LEFT($D15,1))),"")) | ... BI15: =IF(OR($E15="",$F15=""),"",IF(AND(BI$4<=$F15,BI$4+6>=$E15),IF($F15-$E15<=2,"◆",IF($H15="Yes","X",LEFT($D15,1))),""))
A16: T-012 | B16: Build a game engine - Requirements | C16: MJ | D16: Not Started | E16: 46208 | F16: 46217 | G16: 0 | H16: No | I16: =IF(OR($E16="",$F16=""),"",IF(AND(I$4<=$F16,I$4+6>=$E16),IF($F16-$E16<=2,"◆",IF($H16="Yes","X",LEFT($D16,1))),"")) | J16: =IF(OR($E16="",$F16=""),"",IF(AND(J$4<=$F16,J$4+6>=$E16),IF($F16-$E16<=2,"◆",IF($H16="Yes","X",LEFT($D16,1))),"")) | K16: =IF(OR($E16="",$F16=""),"",IF(AND(K$4<=$F16,K$4+6>=$E16),IF($F16-$E16<=2,"◆",IF($H16="Yes","X",LEFT($D16,1))),"")) | L16: =IF(OR($E16="",$F16=""),"",IF(AND(L$4<=$F16,L$4+6>=$E16),IF($F16-$E16<=2,"◆",IF($H16="Yes","X",LEFT($D16,1))),"")) | M16: =IF(OR($E16="",$F16=""),"",IF(AND(M$4<=$F16,M$4+6>=$E16),IF($F16-$E16<=2,"◆",IF($H16="Yes","X",LEFT($D16,1))),"")) | N16: =IF(OR($E16="",$F16=""),"",IF(AND(N$4<=$F16,N$4+6>=$E16),IF($F16-$E16<=2,"◆",IF($H16="Yes","X",LEFT($D16,1))),"")) | O16: =IF(OR($E16="",$F16=""),"",IF(AND(O$4<=$F16,O$4+6>=$E16),IF($F16-$E16<=2,"◆",IF($H16="Yes","X",LEFT($D16,1))),"")) | P16: =IF(OR($E16="",$F16=""),"",IF(AND(P$4<=$F16,P$4+6>=$E16),IF($F16-$E16<=2,"◆",IF($H16="Yes","X",LEFT($D16,1))),"")) | ... BI16: =IF(OR($E16="",$F16=""),"",IF(AND(BI$4<=$F16,BI$4+6>=$E16),IF($F16-$E16<=2,"◆",IF($H16="Yes","X",LEFT($D16,1))),""))
... A113: T-109 | B113: Audit Findings remediation | C113: Kadarkarai | D113: At Risk | E113: 46232 | F113: 46236 | G113: 0.21 | H113: No | I113: =IF(OR($E113="",$F113=""),"",IF(AND(I$4<=$F113,I$4+6>=$E113),IF($F113-$E113<=2,"◆",IF($H113="Yes","X",LEFT($D113,1))),"")) | J113: =IF(OR($E113="",$F113=""),"",IF(AND(J$4<=$F113,J$4+6>=$E113),IF($F113-$E113<=2,"◆",IF($H113="Yes","X",LEFT($D113,1))),"")) | K113: =IF(OR($E113="",$F113=""),"",IF(AND(K$4<=$F113,K$4+6>=$E113),IF($F113-$E113<=2,"◆",IF($H113="Yes","X",LEFT($D113,1))),"")) | L113: =IF(OR($E113="",$F113=""),"",IF(AND(L$4<=$F113,L$4+6>=$E113),IF($F113-$E113<=2,"◆",IF($H113="Yes","X",LEFT($D113,1))),"")) | M113: =IF(OR($E113="",$F113=""),"",IF(AND(M$4<=$F113,M$4+6>=$E113),IF($F113-$E113<=2,"◆",IF($H113="Yes","X",LEFT($D113,1))),"")) | N113: =IF(OR($E113="",$F113=""),"",IF(AND(N$4<=$F113,N$4+6>=$E113),IF($F113-$E113<=2,"◆",IF($H113="Yes","X",LEFT($D113,1))),"")) | O113: =IF(OR($E113="",$F113=""),"",IF(AND(O$4<=$F113,O$4+6>=$E113),IF($F113-$E113<=2,"◆",IF($H113="Yes","X",LEFT($D113,1))),"")) | P113: =IF(OR($E113="",$F113=""),"",IF(AND(P$4<=$F113,P$4+6>=$E113),IF($F113-$E113<=2,"◆",IF($H113="Yes","X",LEFT($D113,1))),"")) | ... BI113: =IF(OR($E113="",$F113=""),"",IF(AND(BI$4<=$F113,BI$4+6>=$E113),IF($F113-$E113<=2,"◆",IF($H113="Yes","X",LEFT($D113,1))),""))
A116: MONTHLY VIEW — Task count active per month (formula)
A117: Month | B117: 46204 | C117: 46235 | D117: 46266 | E117: 46296 | F117: 46327 | G117: 46357 | H117: 46388 | I117: 46419 | J117: 46447 | K117: 46478 | L117: 46508 | M117: 46539
B118: =SUMPRODUCT(('Project Tracker'!$N$5:$N$113<=EOMONTH(B$117,0))*('Project Tracker'!$O$5:$O$113>=B$117)*1) | C118: =SUMPRODUCT(('Project Tracker'!$N$5:$N$113<=EOMONTH(C$117,0))*('Project Tracker'!$O$5:$O$113>=C$117)*1) | D118: =SUMPRODUCT(('Project Tracker'!$N$5:$N$113<=EOMONTH(D$117,0))*('Project Tracker'!$O$5:$O$113>=D$117)*1) | E118: =SUMPRODUCT(('Project Tracker'!$N$5:$N$113<=EOMONTH(E$117,0))*('Project Tracker'!$O$5:$O$113>=E$117)*1) | F118: =SUMPRODUCT(('Project Tracker'!$N$5:$N$113<=EOMONTH(F$117,0))*('Project Tracker'!$O$5:$O$113>=F$117)*1) | G118: =SUMPRODUCT(('Project Tracker'!$N$5:$N$113<=EOMONTH(G$117,0))*('Project Tracker'!$O$5:$O$113>=G$117)*1) | H118: =SUMPRODUCT(('Project Tracker'!$N$5:$N$113<=EOMONTH(H$117,0))*('Project Tracker'!$O$5:$O$113>=H$117)*1) | I118: =SUMPRODUCT(('Project Tracker'!$N$5:$N$113<=EOMONTH(I$117,0))*('Project Tracker'!$O$5:$O$113>=I$117)*1) | ... M118: =SUMPRODUCT(('Project Tracker'!$N$5:$N$113<=EOMONTH(M$117,0))*('Project Tracker'!$O$5:$O$113>=M$117)*1)
A121: QUARTERLY VIEW — Active tasks by quarter
B122: FY27-Q1 | C122: FY27-Q2 | D122: FY27-Q3 | E122: FY27-Q4
A123: Start | B123: 46204 | C123: 46296 | D123: 46388 | E123: 46478
A124: End | B124: 46295 | C124: 46387 | D124: 46477 | E124: 46568
A125: Active Tasks | B125: =SUMPRODUCT(('Project Tracker'!$N$5:$N$113<=B124)*('Project Tracker'!$O$5:$O$113>=B123)*1) | C125: =SUMPRODUCT(('Project Tracker'!$N$5:$N$113<=C124)*('Project Tracker'!$O$5:$O$113>=C123)*1) | D125: =SUMPRODUCT(('Project Tracker'!$N$5:$N$113<=D124)*('Project Tracker'!$O$5:$O$113>=D123)*1) | E125: =SUMPRODUCT(('Project Tracker'!$N$5:$N$113<=E124)*('Project Tracker'!$O$5:$O$113>=E123)*1)

Sheet Resource Planning
A1: RESOURCE PLANNING — CAPACITY & UTILIZATION
A2: Allocated Hours roll up from Project Tracker by Owner. Utilization & Overallocation are formula-driven.
A4: Resource | B4: Role | C4: Capacity (h) | D4: Allocated Hours | E4: Remaining Hours | F4: Utilization % | G4: Vacation (h) | H4: Leave (h) | I4: Overallocated?
A5: Jawahar | B5: Tech Lead — Platform / Core | C5: 5900 | D5: =SUMIF('Project Tracker'!$J$5:$J$113,A5,'Project Tracker'!$R$5:$R$113) | E5: =C5-G5-H5-D5 | F5: =IF((C5-G5-H5)=0,0,D5/(C5-G5-H5)) | G5: 80 | H5: 24 | I5: =IF(D5>(C5-G5-H5),"YES","")
A6: Kadarkarai | B6: Engineer — Platform | C6: 1200 | D6: =SUMIF('Project Tracker'!$J$5:$J$113,A6,'Project Tracker'!$R$5:$R$113) | E6: =C6-G6-H6-D6 | F6: =IF((C6-G6-H6)=0,0,D6/(C6-G6-H6)) | G6: 40 | H6: 24 | I6: =IF(D6>(C6-G6-H6),"YES","")
A7: MJ | B7: EM / Tech Lead — CS | C7: 6850 | D7: =SUMIF('Project Tracker'!$J$5:$J$113,A7,'Project Tracker'!$R$5:$R$113) | E7: =C7-G7-H7-D7 | F7: =IF((C7-G7-H7)=0,0,D7/(C7-G7-H7)) | G7: 80 | H7: 24 | I7: =IF(D7>(C7-G7-H7),"YES","")
A8: Shriguru | B8: Engineer — Achievo / Rewards | C8: 1200 | D8: =SUMIF('Project Tracker'!$J$5:$J$113,A8,'Project Tracker'!$R$5:$R$113) | E8: =C8-G8-H8-D8 | F8: =IF((C8-G8-H8)=0,0,D8/(C8-G8-H8)) | G8: 40 | H8: 24 | I8: =IF(D8>(C8-G8-H8),"YES","")
A9: Siva | B9: Tech Lead — Data / PIS | C9: 3150 | D9: =SUMIF('Project Tracker'!$J$5:$J$113,A9,'Project Tracker'!$R$5:$R$113) | E9: =C9-G9-H9-D9 | F9: =IF((C9-G9-H9)=0,0,D9/(C9-G9-H9)) | G9: 80 | H9: 24 | I9: =IF(D9>(C9-G9-H9),"YES","")
A12: MONTHLY ALLOCATION (Planned Hours by Owner × Month)
A13: Resource | B13: 46204 | C13: 46235 | D13: 46266 | E13: 46296 | F13: 46327 | G13: 46357 | H13: 46388 | I13: 46419 | J13: 46447 | K13: 46478 | L13: 46508 | M13: 46539
A14: Jawahar | B14: =SUMPRODUCT(('Project Tracker'!$J$5:$J$113=A14)*('Project Tracker'!$N$5:$N$113<=EOMONTH(B$13,0))*('Project Tracker'!$O$5:$O$113>=B$13)*('Project Tracker'!$R$5:$R$113)) | C14: =SUMPRODUCT(('Project Tracker'!$J$5:$J$113=A14)*('Project Tracker'!$N$5:$N$113<=EOMONTH(C$13,0))*('Project Tracker'!$O$5:$O$113>=C$13)*('Project Tracker'!$R$5:$R$113)) | D14: =SUMPRODUCT(('Project Tracker'!$J$5:$J$113=A14)*('Project Tracker'!$N$5:$N$113<=EOMONTH(D$13,0))*('Project Tracker'!$O$5:$O$113>=D$13)*('Project Tracker'!$R$5:$R$113)) | E14: =SUMPRODUCT(('Project Tracker'!$J$5:$J$113=A14)*('Project Tracker'!$N$5:$N$113<=EOMONTH(E$13,0))*('Project Tracker'!$O$5:$O$113>=E$13)*('Project Tracker'!$R$5:$R$113)) | F14: =SUMPRODUCT(('Project Tracker'!$J$5:$J$113=A14)*('Project Tracker'!$N$5:$N$113<=EOMONTH(F$13,0))*('Project Tracker'!$O$5:$O$113>=F$13)*('Project Tracker'!$R$5:$R$113)) | G14: =SUMPRODUCT(('Project Tracker'!$J$5:$J$113=A14)*('Project Tracker'!$N$5:$N$113<=EOMONTH(G$13,0))*('Project Tracker'!$O$5:$O$113>=G$13)*('Project Tracker'!$R$5:$R$113)) | H14: =SUMPRODUCT(('Project Tracker'!$J$5:$J$113=A14)*('Project Tracker'!$N$5:$N$113<=EOMONTH(H$13,0))*('Project Tracker'!$O$5:$O$113>=H$13)*('Project Tracker'!$R$5:$R$113)) | I14: =SUMPRODUCT(('Project Tracker'!$J$5:$J$113=A14)*('Project Tracker'!$N$5:$N$113<=EOMONTH(I$13,0))*('Project Tracker'!$O$5:$O$113>=I$13)*('Project Tracker'!$R$5:$R$113)) | J14: =SUMPRODUCT(('Project Tracker'!$J$5:$J$113=A14)*('Project Tracker'!$N$5:$N$113<=EOMONTH(J$13,0))*('Project Tracker'!$O$5:$O$113>=J$13)*('Project Tracker'!$R$5:$R$113)) | K14: =SUMPRODUCT(('Project Tracker'!$J$5:$J$113=A14)*('Project Tracker'!$N$5:$N$113<=EOMONTH(K$13,0))*('Project Tracker'!$O$5:$O$113>=K$13)*('Project Tracker'!$R$5:$R$113)) | L14: =SUMPRODUCT(('Project Tracker'!$J$5:$J$113=A14)*('Project Tracker'!$N$5:$N$113<=EOMONTH(L$13,0))*('Project Tracker'!$O$5:$O$113>=L$13)*('Project Tracker'!$R$5:$R$113)) | M14: =SUMPRODUCT(('Project Tracker'!$J$5:$J$113=A14)*('Project Tracker'!$N$5:$N$113<=EOMONTH(M$13,0))*('Project Tracker'!$O$5:$O$113>=M$13)*('Project Tracker'!$R$5:$R$113))
A15: Kadarkarai | B15: =SUMPRODUCT(('Project Tracker'!$J$5:$J$113=A15)*('Project Tracker'!$N$5:$N$113<=EOMONTH(B$13,0))*('Project Tracker'!$O$5:$O$113>=B$13)*('Project Tracker'!$R$5:$R$113)) | C15: =SUMPRODUCT(('Project Tracker'!$J$5:$J$113=A15)*('Project Tracker'!$N$5:$N$113<=EOMONTH(C$13,0))*('Project Tracker'!$O$5:$O$113>=C$13)*('Project Tracker'!$R$5:$R$113)) | D15: =SUMPRODUCT(('Project Tracker'!$J$5:$J$113=A15)*('Project Tracker'!$N$5:$N$113<=EOMONTH(D$13,0))*('Project Tracker'!$O$5:$O$113>=D$13)*('Project Tracker'!$R$5:$R$113)) | E15: =SUMPRODUCT(('Project Tracker'!$J$5:$J$113=A15)*('Project Tracker'!$N$5:$N$113<=EOMONTH(E$13,0))*('Project Tracker'!$O$5:$O$113>=E$13)*('Project Tracker'!$R$5:$R$113)) | F15: =SUMPRODUCT(('Project Tracker'!$J$5:$J$113=A15)*('Project Tracker'!$N$5:$N$113<=EOMONTH(F$13,0))*('Project Tracker'!$O$5:$O$113>=F$13)*('Project Tracker'!$R$5:$R$113)) | G15: =SUMPRODUCT(('Project Tracker'!$J$5:$J$113=A15)*('Project Tracker'!$N$5:$N$113<=EOMONTH(G$13,0))*('Project Tracker'!$O$5:$O$113>=G$13)*('Project Tracker'!$R$5:$R$113)) | H15: =SUMPRODUCT(('Project Tracker'!$J$5:$J$113=A15)*('Project Tracker'!$N$5:$N$113<=EOMONTH(H$13,0))*('Project Tracker'!$O$5:$O$113>=H$13)*('Project Tracker'!$R$5:$R$113)) | I15: =SUMPRODUCT(('Project Tracker'!$J$5:$J$113=A15)*('Project Tracker'!$N$5:$N$113<=EOMONTH(I$13,0))*('Project Tracker'!$O$5:$O$113>=I$13)*('Project Tracker'!$R$5:$R$113)) | J15: =SUMPRODUCT(('Project Tracker'!$J$5:$J$113=A15)*('Project Tracker'!$N$5:$N$113<=EOMONTH(J$13,0))*('Project Tracker'!$O$5:$O$113>=J$13)*('Project Tracker'!$R$5:$R$113)) | K15: =SUMPRODUCT(('Project Tracker'!$J$5:$J$113=A15)*('Project Tracker'!$N$5:$N$113<=EOMONTH(K$13,0))*('Project Tracker'!$O$5:$O$113>=K$13)*('Project Tracker'!$R$5:$R$113)) | L15: =SUMPRODUCT(('Project Tracker'!$J$5:$J$113=A15)*('Project Tracker'!$N$5:$N$113<=EOMONTH(L$13,0))*('Project Tracker'!$O$5:$O$113>=L$13)*('Project Tracker'!$R$5:$R$113)) | M15: =SUMPRODUCT(('Project Tracker'!$J$5:$J$113=A15)*('Project Tracker'!$N$5:$N$113<=EOMONTH(M$13,0))*('Project Tracker'!$O$5:$O$113>=M$13)*('Project Tracker'!$R$5:$R$113))
A16: MJ | B16: =SUMPRODUCT(('Project Tracker'!$J$5:$J$113=A16)*('Project Tracker'!$N$5:$N$113<=EOMONTH(B$13,0))*('Project Tracker'!$O$5:$O$113>=B$13)*('Project Tracker'!$R$5:$R$113)) | C16: =SUMPRODUCT(('Project Tracker'!$J$5:$J$113=A16)*('Project Tracker'!$N$5:$N$113<=EOMONTH(C$13,0))*('Project Tracker'!$O$5:$O$113>=C$13)*('Project Tracker'!$R$5:$R$113)) | D16: =SUMPRODUCT(('Project Tracker'!$J$5:$J$113=A16)*('Project Tracker'!$N$5:$N$113<=EOMONTH(D$13,0))*('Project Tracker'!$O$5:$O$113>=D$13)*('Project Tracker'!$R$5:$R$113)) | E16: =SUMPRODUCT(('Project Tracker'!$J$5:$J$113=A16)*('Project Tracker'!$N$5:$N$113<=EOMONTH(E$13,0))*('Project Tracker'!$O$5:$O$113>=E$13)*('Project Tracker'!$R$5:$R$113)) | F16: =SUMPRODUCT(('Project Tracker'!$J$5:$J$113=A16)*('Project Tracker'!$N$5:$N$113<=EOMONTH(F$13,0))*('Project Tracker'!$O$5:$O$113>=F$13)*('Project Tracker'!$R$5:$R$113)) | G16: =SUMPRODUCT(('Project Tracker'!$J$5:$J$113=A16)*('Project Tracker'!$N$5:$N$113<=EOMONTH(G$13,0))*('Project Tracker'!$O$5:$O$113>=G$13)*('Project Tracker'!$R$5:$R$113)) | H16: =SUMPRODUCT(('Project Tracker'!$J$5:$J$113=A16)*('Project Tracker'!$N$5:$N$113<=EOMONTH(H$13,0))*('Project Tracker'!$O$5:$O$113>=H$13)*('Project Tracker'!$R$5:$R$113)) | I16: =SUMPRODUCT(('Project Tracker'!$J$5:$J$113=A16)*('Project Tracker'!$N$5:$N$113<=EOMONTH(I$13,0))*('Project Tracker'!$O$5:$O$113>=I$13)*('Project Tracker'!$R$5:$R$113)) | J16: =SUMPRODUCT(('Project Tracker'!$J$5:$J$113=A16)*('Project Tracker'!$N$5:$N$113<=EOMONTH(J$13,0))*('Project Tracker'!$O$5:$O$113>=J$13)*('Project Tracker'!$R$5:$R$113)) | K16: =SUMPRODUCT(('Project Tracker'!$J$5:$J$113=A16)*('Project Tracker'!$N$5:$N$113<=EOMONTH(K$13,0))*('Project Tracker'!$O$5:$O$113>=K$13)*('Project Tracker'!$R$5:$R$113)) | L16: =SUMPRODUCT(('Project Tracker'!$J$5:$J$113=A16)*('Project Tracker'!$N$5:$N$113<=EOMONTH(L$13,0))*('Project Tracker'!$O$5:$O$113>=L$13)*('Project Tracker'!$R$5:$R$113)) | M16: =SUMPRODUCT(('Project Tracker'!$J$5:$J$113=A16)*('Project Tracker'!$N$5:$N$113<=EOMONTH(M$13,0))*('Project Tracker'!$O$5:$O$113>=M$13)*('Project Tracker'!$R$5:$R$113))
A17: Shriguru | B17: =SUMPRODUCT(('Project Tracker'!$J$5:$J$113=A17)*('Project Tracker'!$N$5:$N$113<=EOMONTH(B$13,0))*('Project Tracker'!$O$5:$O$113>=B$13)*('Project Tracker'!$R$5:$R$113)) | C17: =SUMPRODUCT(('Project Tracker'!$J$5:$J$113=A17)*('Project Tracker'!$N$5:$N$113<=EOMONTH(C$13,0))*('Project Tracker'!$O$5:$O$113>=C$13)*('Project Tracker'!$R$5:$R$113)) | D17: =SUMPRODUCT(('Project Tracker'!$J$5:$J$113=A17)*('Project Tracker'!$N$5:$N$113<=EOMONTH(D$13,0))*('Project Tracker'!$O$5:$O$113>=D$13)*('Project Tracker'!$R$5:$R$113)) | E17: =SUMPRODUCT(('Project Tracker'!$J$5:$J$113=A17)*('Project Tracker'!$N$5:$N$113<=EOMONTH(E$13,0))*('Project Tracker'!$O$5:$O$113>=E$13)*('Project Tracker'!$R$5:$R$113)) | F17: =SUMPRODUCT(('Project Tracker'!$J$5:$J$113=A17)*('Project Tracker'!$N$5:$N$113<=EOMONTH(F$13,0))*('Project Tracker'!$O$5:$O$113>=F$13)*('Project Tracker'!$R$5:$R$113)) | G17: =SUMPRODUCT(('Project Tracker'!$J$5:$J$113=A17)*('Project Tracker'!$N$5:$N$113<=EOMONTH(G$13,0))*('Project Tracker'!$O$5:$O$113>=G$13)*('Project Tracker'!$R$5:$R$113)) | H17: =SUMPRODUCT(('Project Tracker'!$J$5:$J$113=A17)*('Project Tracker'!$N$5:$N$113<=EOMONTH(H$13,0))*('Project Tracker'!$O$5:$O$113>=H$13)*('Project Tracker'!$R$5:$R$113)) | I17: =SUMPRODUCT(('Project Tracker'!$J$5:$J$113=A17)*('Project Tracker'!$N$5:$N$113<=EOMONTH(I$13,0))*('Project Tracker'!$O$5:$O$113>=I$13)*('Project Tracker'!$R$5:$R$113)) | J17: =SUMPRODUCT(('Project Tracker'!$J$5:$J$113=A17)*('Project Tracker'!$N$5:$N$113<=EOMONTH(J$13,0))*('Project Tracker'!$O$5:$O$113>=J$13)*('Project Tracker'!$R$5:$R$113)) | K17: =SUMPRODUCT(('Project Tracker'!$J$5:$J$113=A17)*('Project Tracker'!$N$5:$N$113<=EOMONTH(K$13,0))*('Project Tracker'!$O$5:$O$113>=K$13)*('Project Tracker'!$R$5:$R$113)) | L17: =SUMPRODUCT(('Project Tracker'!$J$5:$J$113=A17)*('Project Tracker'!$N$5:$N$113<=EOMONTH(L$13,0))*('Project Tracker'!$O$5:$O$113>=L$13)*('Project Tracker'!$R$5:$R$113)) | M17: =SUMPRODUCT(('Project Tracker'!$J$5:$J$113=A17)*('Project Tracker'!$N$5:$N$113<=EOMONTH(M$13,0))*('Project Tracker'!$O$5:$O$113>=M$13)*('Project Tracker'!$R$5:$R$113))
A18: Siva | B18: =SUMPRODUCT(('Project Tracker'!$J$5:$J$113=A18)*('Project Tracker'!$N$5:$N$113<=EOMONTH(B$13,0))*('Project Tracker'!$O$5:$O$113>=B$13)*('Project Tracker'!$R$5:$R$113)) | C18: =SUMPRODUCT(('Project Tracker'!$J$5:$J$113=A18)*('Project Tracker'!$N$5:$N$113<=EOMONTH(C$13,0))*('Project Tracker'!$O$5:$O$113>=C$13)*('Project Tracker'!$R$5:$R$113)) | D18: =SUMPRODUCT(('Project Tracker'!$J$5:$J$113=A18)*('Project Tracker'!$N$5:$N$113<=EOMONTH(D$13,0))*('Project Tracker'!$O$5:$O$113>=D$13)*('Project Tracker'!$R$5:$R$113)) | E18: =SUMPRODUCT(('Project Tracker'!$J$5:$J$113=A18)*('Project Tracker'!$N$5:$N$113<=EOMONTH(E$13,0))*('Project Tracker'!$O$5:$O$113>=E$13)*('Project Tracker'!$R$5:$R$113)) | F18: =SUMPRODUCT(('Project Tracker'!$J$5:$J$113=A18)*('Project Tracker'!$N$5:$N$113<=EOMONTH(F$13,0))*('Project Tracker'!$O$5:$O$113>=F$13)*('Project Tracker'!$R$5:$R$113)) | G18: =SUMPRODUCT(('Project Tracker'!$J$5:$J$113=A18)*('Project Tracker'!$N$5:$N$113<=EOMONTH(G$13,0))*('Project Tracker'!$O$5:$O$113>=G$13)*('Project Tracker'!$R$5:$R$113)) | H18: =SUMPRODUCT(('Project Tracker'!$J$5:$J$113=A18)*('Project Tracker'!$N$5:$N$113<=EOMONTH(H$13,0))*('Project Tracker'!$O$5:$O$113>=H$13)*('Project Tracker'!$R$5:$R$113)) | I18: =SUMPRODUCT(('Project Tracker'!$J$5:$J$113=A18)*('Project Tracker'!$N$5:$N$113<=EOMONTH(I$13,0))*('Project Tracker'!$O$5:$O$113>=I$13)*('Project Tracker'!$R$5:$R$113)) | J18: =SUMPRODUCT(('Project Tracker'!$J$5:$J$113=A18)*('Project Tracker'!$N$5:$N$113<=EOMONTH(J$13,0))*('Project Tracker'!$O$5:$O$113>=J$13)*('Project Tracker'!$R$5:$R$113)) | K18: =SUMPRODUCT(('Project Tracker'!$J$5:$J$113=A18)*('Project Tracker'!$N$5:$N$113<=EOMONTH(K$13,0))*('Project Tracker'!$O$5:$O$113>=K$13)*('Project Tracker'!$R$5:$R$113)) | L18: =SUMPRODUCT(('Project Tracker'!$J$5:$J$113=A18)*('Project Tracker'!$N$5:$N$113<=EOMONTH(L$13,0))*('Project Tracker'!$O$5:$O$113>=L$13)*('Project Tracker'!$R$5:$R$113)) | M18: =SUMPRODUCT(('Project Tracker'!$J$5:$J$113=A18)*('Project Tracker'!$N$5:$N$113<=EOMONTH(M$13,0))*('Project Tracker'!$O$5:$O$113>=M$13)*('Project Tracker'!$R$5:$R$113))
A21: QUARTER-WISE UTILIZATION %
A22: Resource | B22: FY27-Q1 | C22: FY27-Q2 | D22: FY27-Q3 | E22: FY27-Q4
A23: Jawahar | B23: =IF(C5=0,0,SUM(B14:D14)/(C5/4)) | C23: =IF(C5=0,0,SUM(E14:G14)/(C5/4)) | D23: =IF(C5=0,0,SUM(H14:J14)/(C5/4)) | E23: =IF(C5=0,0,SUM(K14:M14)/(C5/4))
A24: Kadarkarai | B24: =IF(C6=0,0,SUM(B15:D15)/(C6/4)) | C24: =IF(C6=0,0,SUM(E15:G15)/(C6/4)) | D24: =IF(C6=0,0,SUM(H15:J15)/(C6/4)) | E24: =IF(C6=0,0,SUM(K15:M15)/(C6/4))
A25: MJ | B25: =IF(C7=0,0,SUM(B16:D16)/(C7/4)) | C25: =IF(C7=0,0,SUM(E16:G16)/(C7/4)) | D25: =IF(C7=0,0,SUM(H16:J16)/(C7/4)) | E25: =IF(C7=0,0,SUM(K16:M16)/(C7/4))
A26: Shriguru | B26: =IF(C8=0,0,SUM(B17:D17)/(C8/4)) | C26: =IF(C8=0,0,SUM(E17:G17)/(C8/4)) | D26: =IF(C8=0,0,SUM(H17:J17)/(C8/4)) | E26: =IF(C8=0,0,SUM(K17:M17)/(C8/4))
A27: Siva | B27: =IF(C9=0,0,SUM(B18:D18)/(C9/4)) | C27: =IF(C9=0,0,SUM(E18:G18)/(C9/4)) | D27: =IF(C9=0,0,SUM(H18:J18)/(C9/4)) | E27: =IF(C9=0,0,SUM(K18:M18)/(C9/4))

Sheet Milestones
A1: MILESTONES — FY27 GOVERNANCE
A2: Delay and 'Upcoming within 14 days' are formula-driven.
A4: Milestone ID | B4: Milestone | C4: Owner | D4: Planned Date | E4: Actual Date | F4: Status | G4: Delay (days) | H4: Upcoming within 14 days
A5: M-01 | B5: FY27 Planning Baseline Locked (FY27 V1) | C5: Jawahar | D5: 46213 | E5: 46211 | F5: Completed | G5: =IF(E5<>"",E5-D5,IF(AND(D5<TODAY(),F5<>"Completed"),TODAY()-D5,0)) | H5: =IF(AND(D5>=TODAY(),D5<=TODAY()+14,F5<>"Completed"),"YES","")
A6: M-02 | B6: Q1 Governance Checkpoint | C6: Kadarkarai | D6: 46290 | F6: Not Started | G6: =IF(E6<>"",E6-D6,IF(AND(D6<TODAY(),F6<>"Completed"),TODAY()-D6,0)) | H6: =IF(AND(D6>=TODAY(),D6<=TODAY()+14,F6<>"Completed"),"YES","")
A7: M-03 | B7: Q2 Governance Checkpoint | C7: MJ | D7: 46374 | F7: Not Started | G7: =IF(E7<>"",E7-D7,IF(AND(D7<TODAY(),F7<>"Completed"),TODAY()-D7,0)) | H7: =IF(AND(D7>=TODAY(),D7<=TODAY()+14,F7<>"Completed"),"YES","")
A8: M-04 | B8: Q3 Governance Checkpoint | C8: Shriguru | D8: 46466 | F8: Not Started | G8: =IF(E8<>"",E8-D8,IF(AND(D8<TODAY(),F8<>"Completed"),TODAY()-D8,0)) | H8: =IF(AND(D8>=TODAY(),D8<=TODAY()+14,F8<>"Completed"),"YES","")
A9: M-05 | B9: Q4 / FY27 Closeout | C9: Siva | D9: 46568 | F9: Not Started | G9: =IF(E9<>"",E9-D9,IF(AND(D9<TODAY(),F9<>"Completed"),TODAY()-D9,0)) | H9: =IF(AND(D9>=TODAY(),D9<=TODAY()+14,F9<>"Completed"),"YES","")
A10: M-06 | B10: CS 1.0 — Q1 exit gate | C10: Jawahar | D10: 46295 | F10: In Progress | G10: =IF(E10<>"",E10-D10,IF(AND(D10<TODAY(),F10<>"Completed"),TODAY()-D10,0)) | H10: =IF(AND(D10>=TODAY(),D10<=TODAY()+14,F10<>"Completed"),"YES","")
A11: M-07 | B11: CS 1.0 — H1 checkpoint | C11: Kadarkarai | D11: 46387 | F11: Not Started | G11: =IF(E11<>"",E11-D11,IF(AND(D11<TODAY(),F11<>"Completed"),TODAY()-D11,0)) | H11: =IF(AND(D11>=TODAY(),D11<=TODAY()+14,F11<>"Completed"),"YES","")
A12: M-08 | B12: CS 2.0 — Q1 exit gate | C12: MJ | D12: 46295 | F12: In Progress | G12: =IF(E12<>"",E12-D12,IF(AND(D12<TODAY(),F12<>"Completed"),TODAY()-D12,0)) | H12: =IF(AND(D12>=TODAY(),D12<=TODAY()+14,F12<>"Completed"),"YES","")
A13: M-09 | B13: CS 2.0 — H1 checkpoint | C13: Shriguru | D13: 46387 | F13: Not Started | G13: =IF(E13<>"",E13-D13,IF(AND(D13<TODAY(),F13<>"Completed"),TODAY()-D13,0)) | H13: =IF(AND(D13>=TODAY(),D13<=TODAY()+14,F13<>"Completed"),"YES","")
A14: M-10 | B14: CS 2.0 Achievo — Q1 exit gate | C14: Siva | D14: 46295 | F14: In Progress | G14: =IF(E14<>"",E14-D14,IF(AND(D14<TODAY(),F14<>"Completed"),TODAY()-D14,0)) | H14: =IF(AND(D14>=TODAY(),D14<=TODAY()+14,F14<>"Completed"),"YES","")
A15: M-11 | B15: CS 2.0 Achievo — H1 checkpoint | C15: Jawahar | D15: 46387 | F15: Not Started | G15: =IF(E15<>"",E15-D15,IF(AND(D15<TODAY(),F15<>"Completed"),TODAY()-D15,0)) | H15: =IF(AND(D15>=TODAY(),D15<=TODAY()+14,F15<>"Completed"),"YES","")
A16: M-12 | B16: CS 2.0 Core — Q1 exit gate | C16: Kadarkarai | D16: 46295 | F16: In Progress | G16: =IF(E16<>"",E16-D16,IF(AND(D16<TODAY(),F16<>"Completed"),TODAY()-D16,0)) | H16: =IF(AND(D16>=TODAY(),D16<=TODAY()+14,F16<>"Completed"),"YES","")
A17: M-13 | B17: CS 2.0 Core — H1 checkpoint | C17: MJ | D17: 46387 | F17: Not Started | G17: =IF(E17<>"",E17-D17,IF(AND(D17<TODAY(),F17<>"Completed"),TODAY()-D17,0)) | H17: =IF(AND(D17>=TODAY(),D17<=TODAY()+14,F17<>"Completed"),"YES","")
... A27: M-23 | B27: Critical: Achievo Mobile App Upgrades and Store Policy Compliance Upda | C27: MJ | D27: 46277 | F27: Not Started | G27: =IF(E27<>"",E27-D27,IF(AND(D27<TODAY(),F27<>"Completed"),TODAY()-D27,0)) | H27: =IF(AND(D27>=TODAY(),D27<=TODAY()+14,F27<>"Completed"),"YES","")

Sheet Risks & Issues
A1: RISKS & ISSUES REGISTER
A2: Severity = Impact × Probability (formula). High severity auto-highlighted.
A4: Risk ID | B4: Description | C4: Impact | D4: Probability | E4: Severity | F4: Owner | G4: Mitigation | H4: Status | I4: Review Date
A5: R-01 | B5: CS 1.0 decommission (BRIKS / Coupon / OTP) may disrupt CS 2.0 dual-run | C5: High | D5: High | E5: =IF(OR(C5="",D5=""),"",IF((IF(C5="High",3,IF(C5="Medium",2,1)))*(IF(D5="High",3,IF(D5="Medium",2,1)))>=9,"Critical",IF((IF(C5="High",3,IF(C5="Medium",2,1)))*(IF(D5="High",3,IF(D5="Medium",2,1)))>=6,"High",IF((IF(C5="High",3,IF(C5="Medium",2,1)))*(IF(D5="High",3,IF(D5="Medium",2,1)))>=3,"Medium","Low")))) | F5: MJ | G5: Owned by MJ; track in weekly governance; link to FY27 V1 source items. | H5: Open | I5: 46237
A6: R-02 | B6: ERP / Salesforce connector scope (CS 2.0) under-estimated vs. planned hours | C6: High | D6: Medium | E6: =IF(OR(C6="",D6=""),"",IF((IF(C6="High",3,IF(C6="Medium",2,1)))*(IF(D6="High",3,IF(D6="Medium",2,1)))>=9,"Critical",IF((IF(C6="High",3,IF(C6="Medium",2,1)))*(IF(D6="High",3,IF(D6="Medium",2,1)))>=6,"High",IF((IF(C6="High",3,IF(C6="Medium",2,1)))*(IF(D6="High",3,IF(D6="Medium",2,1)))>=3,"Medium","Low")))) | F6: MJ | G6: Owned by MJ; track in weekly governance; link to FY27 V1 source items. | H6: Watching | I6: 46251
A7: R-03 | B7: PIS Journey Builder prediction agents depend on unstable partner data quality | C7: High | D7: High | E7: =IF(OR(C7="",D7=""),"",IF((IF(C7="High",3,IF(C7="Medium",2,1)))*(IF(D7="High",3,IF(D7="Medium",2,1)))>=9,"Critical",IF((IF(C7="High",3,IF(C7="Medium",2,1)))*(IF(D7="High",3,IF(D7="Medium",2,1)))>=6,"High",IF((IF(C7="High",3,IF(C7="Medium",2,1)))*(IF(D7="High",3,IF(D7="Medium",2,1)))>=3,"Medium","Low")))) | F7: MJ | G7: Owned by MJ; track in weekly governance; link to FY27 V1 source items. | H7: Mitigating | I7: 46244
A8: R-04 | B8: Internal VAPT + remediation capacity contention with feature delivery | C8: Medium | D8: High | E8: =IF(OR(C8="",D8=""),"",IF((IF(C8="High",3,IF(C8="Medium",2,1)))*(IF(D8="High",3,IF(D8="Medium",2,1)))>=9,"Critical",IF((IF(C8="High",3,IF(C8="Medium",2,1)))*(IF(D8="High",3,IF(D8="Medium",2,1)))>=6,"High",IF((IF(C8="High",3,IF(C8="Medium",2,1)))*(IF(D8="High",3,IF(D8="Medium",2,1)))>=3,"Medium","Low")))) | F8: Jawahar | G8: Owned by Jawahar; track in weekly governance; link to FY27 V1 source items. | H8: Open | I8: 46270
A9: R-05 | B9: Include=Pending items without decision are inflating Q1 commitment risk | C9: High | D9: Medium | E9: =IF(OR(C9="",D9=""),"",IF((IF(C9="High",3,IF(C9="Medium",2,1)))*(IF(D9="High",3,IF(D9="Medium",2,1)))>=9,"Critical",IF((IF(C9="High",3,IF(C9="Medium",2,1)))*(IF(D9="High",3,IF(D9="Medium",2,1)))>=6,"High",IF((IF(C9="High",3,IF(C9="Medium",2,1)))*(IF(D9="High",3,IF(D9="Medium",2,1)))>=3,"Medium","Low")))) | F9: MJ | G9: Owned by MJ; track in weekly governance; link to FY27 V1 source items. | H9: Open | I9: 46273
A10: R-06 | B10: TBD-hour items prevent reliable capacity & burn forecasting | C10: Medium | D10: High | E10: =IF(OR(C10="",D10=""),"",IF((IF(C10="High",3,IF(C10="Medium",2,1)))*(IF(D10="High",3,IF(D10="Medium",2,1)))>=9,"Critical",IF((IF(C10="High",3,IF(C10="Medium",2,1)))*(IF(D10="High",3,IF(D10="Medium",2,1)))>=6,"High",IF((IF(C10="High",3,IF(C10="Medium",2,1)))*(IF(D10="High",3,IF(D10="Medium",2,1)))>=3,"Medium","Low")))) | F10: MJ | G10: Owned by MJ; track in weekly governance; link to FY27 V1 source items. | H10: Open | I10: 46238
A11: R-07 | B11: CS 2.0 Core tech maintenance backlog crowding new-feature sprints | C11: High | D11: Medium | E11: =IF(OR(C11="",D11=""),"",IF((IF(C11="High",3,IF(C11="Medium",2,1)))*(IF(D11="High",3,IF(D11="Medium",2,1)))>=9,"Critical",IF((IF(C11="High",3,IF(C11="Medium",2,1)))*(IF(D11="High",3,IF(D11="Medium",2,1)))>=6,"High",IF((IF(C11="High",3,IF(C11="Medium",2,1)))*(IF(D11="High",3,IF(D11="Medium",2,1)))>=3,"Medium","Low")))) | F11: MJ | G11: Owned by MJ; track in weekly governance; link to FY27 V1 source items. | H11: Open | I11: 46241
A12: R-08 | B12: Achievo / Rewards stream under-staffed relative to CS 2.0 Achievo scope | C12: Medium | D12: Medium | E12: =IF(OR(C12="",D12=""),"",IF((IF(C12="High",3,IF(C12="Medium",2,1)))*(IF(D12="High",3,IF(D12="Medium",2,1)))>=9,"Critical",IF((IF(C12="High",3,IF(C12="Medium",2,1)))*(IF(D12="High",3,IF(D12="Medium",2,1)))>=6,"High",IF((IF(C12="High",3,IF(C12="Medium",2,1)))*(IF(D12="High",3,IF(D12="Medium",2,1)))>=3,"Medium","Low")))) | F12: MJ | G12: Owned by MJ; track in weekly governance; link to FY27 V1 source items. | H12: Mitigating | I12: 46250
A13: R-09 | B13: Q1 Critical mass may create spillover into Q2 without rebaseline | C13: High | D13: High | E13: =IF(OR(C13="",D13=""),"",IF((IF(C13="High",3,IF(C13="Medium",2,1)))*(IF(D13="High",3,IF(D13="Medium",2,1)))>=9,"Critical",IF((IF(C13="High",3,IF(C13="Medium",2,1)))*(IF(D13="High",3,IF(D13="Medium",2,1)))>=6,"High",IF((IF(C13="High",3,IF(C13="Medium",2,1)))*(IF(D13="High",3,IF(D13="Medium",2,1)))>=3,"Medium","Low")))) | F13: Jawahar | G13: Owned by Jawahar; track in weekly governance; link to FY27 V1 source items. | H13: Open | I13: 46271
A14: R-10 | B14: Cross-project dependency chains (same-owner serial work) create idle wait | C14: Medium | D14: Medium | E14: =IF(OR(C14="",D14=""),"",IF((IF(C14="High",3,IF(C14="Medium",2,1)))*(IF(D14="High",3,IF(D14="Medium",2,1)))>=9,"Critical",IF((IF(C14="High",3,IF(C14="Medium",2,1)))*(IF(D14="High",3,IF(D14="Medium",2,1)))>=6,"High",IF((IF(C14="High",3,IF(C14="Medium",2,1)))*(IF(D14="High",3,IF(D14="Medium",2,1)))>=3,"Medium","Low")))) | F14: Jawahar | G14: Owned by Jawahar; track in weekly governance; link to FY27 V1 source items. | H14: Mitigating | I14: 46270
A15: R-11 | B15: Description gaps on large-hour items reduce estimate confidence | C15: Low | D15: Medium | E15: =IF(OR(C15="",D15=""),"",IF((IF(C15="High",3,IF(C15="Medium",2,1)))*(IF(D15="High",3,IF(D15="Medium",2,1)))>=9,"Critical",IF((IF(C15="High",3,IF(C15="Medium",2,1)))*(IF(D15="High",3,IF(D15="Medium",2,1)))>=6,"High",IF((IF(C15="High",3,IF(C15="Medium",2,1)))*(IF(D15="High",3,IF(D15="Medium",2,1)))>=3,"Medium","Low")))) | F15: MJ | G15: Owned by MJ; track in weekly governance; link to FY27 V1 source items. | H15: Open | I15: 46250
A16: R-12 | B16: Mobile / Core / Data flag sparsity weakens workstream reporting | C16: Low | D16: Low | E16: =IF(OR(C16="",D16=""),"",IF((IF(C16="High",3,IF(C16="Medium",2,1)))*(IF(D16="High",3,IF(D16="Medium",2,1)))>=9,"Critical",IF((IF(C16="High",3,IF(C16="Medium",2,1)))*(IF(D16="High",3,IF(D16="Medium",2,1)))>=6,"High",IF((IF(C16="High",3,IF(C16="Medium",2,1)))*(IF(D16="High",3,IF(D16="Medium",2,1)))>=3,"Medium","Low")))) | F16: Shriguru | G16: Owned by Shriguru; track in weekly governance; link to FY27 V1 source items. | H16: Open | I16: 46273
... A22: R-20 | B22: Delivery risk linked from tracker tasks (R-20) | C22: High | D22: Medium | E22: =IF(OR(C22="",D22=""),"",IF((IF(C22="High",3,IF(C22="Medium",2,1)))*(IF(D22="High",3,IF(D22="Medium",2,1)))>=9,"Critical",IF((IF(C22="High",3,IF(C22="Medium",2,1)))*(IF(D22="High",3,IF(D22="Medium",2,1)))>=6,"High",IF((IF(C22="High",3,IF(C22="Medium",2,1)))*(IF(D22="High",3,IF(D22="Medium",2,1)))>=3,"Medium","Low")))) | F22: Jawahar | G22: Review linked tasks; confirm Include and dates. | H22: Open | I22: 46243

Sheet Dependencies
A1: DEPENDENCIES REGISTER
A2: Overdue dependencies (Expected Date < TODAY and Status ≠ Satisfied) are highlighted.
A4: Dependency ID | B4: Task | C4: Depends On | D4: Owner | E4: Expected Date | F4: Actual Date | G4: Status
A5: D-001 | B5: T-002 | C5: T-001 | D5: MJ | E5: 46293 | G5: =IF(F5<>"","Satisfied",IF(E5<TODAY(),"Overdue","Open"))
A6: D-002 | B6: T-003 | C6: T-002 | D6: MJ | E6: 46226 | G6: =IF(F6<>"","Satisfied",IF(E6<TODAY(),"Overdue","Open"))
A7: D-003 | B7: T-004 | C7: T-003 | D7: MJ | E7: 46242 | G7: =IF(F7<>"","Satisfied",IF(E7<TODAY(),"Overdue","Open"))
A8: D-004 | B8: T-005 | C8: T-004 | D8: MJ | E8: 46244 | G8: =IF(F8<>"","Satisfied",IF(E8<TODAY(),"Overdue","Open"))
A9: D-005 | B9: T-007 | C9: T-006 | D9: MJ | E9: 46291 | G9: =IF(F9<>"","Satisfied",IF(E9<TODAY(),"Overdue","Open"))
A10: D-006 | B10: T-008 | C10: T-007 | D10: MJ | E10: 46263 | G10: =IF(F10<>"","Satisfied",IF(E10<TODAY(),"Overdue","Open"))
A11: D-007 | B11: T-009 | C11: T-008 | D11: MJ | E11: 46269 | G11: =IF(F11<>"","Satisfied",IF(E11<TODAY(),"Overdue","Open"))
A12: D-008 | B12: T-010 | C12: T-009 | D12: Jawahar | E12: 46261 | G12: =IF(F12<>"","Satisfied",IF(E12<TODAY(),"Overdue","Open"))
A13: D-009 | B13: T-011 | C13: T-010 | D13: Jawahar | E13: 46277 | G13: =IF(F13<>"","Satisfied",IF(E13<TODAY(),"Overdue","Open"))
A14: D-010 | B14: T-012 | C14: T-011 | D14: MJ | E14: 46284 | G14: =IF(F14<>"","Satisfied",IF(E14<TODAY(),"Overdue","Open"))
A15: D-011 | B15: T-013 | C15: T-012 | D15: MJ | E15: 46217 | G15: =IF(F15<>"","Satisfied",IF(E15<TODAY(),"Overdue","Open"))
A16: D-012 | B16: T-014 | C16: T-013 | D16: MJ | E16: 46286 | G16: =IF(F16<>"","Satisfied",IF(E16<TODAY(),"Overdue","Open"))
... A103: D-099 | B103: T-109 | C103: T-108 | D103: Kadarkarai | E103: 46254 | G103: =IF(F103<>"","Satisfied",IF(E103<TODAY(),"Overdue","Open"))

Sheet Lookup Lists
A1: LOOKUP LISTS — Dropdown Source Values
A2: Maintain these lists to drive Project Tracker dropdowns and named ranges.
A4: Owners | B4: Priority | C4: Status | D4: Teams | E4: Projects | F4: Releases | G4: Sprint | H4: Phase | I4: Workstream | J4: Impact | K4: Probability | L4: Risk Status | M4: Dep Status | N4: Category
A5: Jawahar | B5: Critical | C5: Not Started | D5: Platform | E5: CS 1.0 | F5: R26.Q1 | G5: Sprint 01 | H5: Discovery | I5: Product Delivery | J5: High | K5: High | L5: Open | M5: Open | N5: Funct Enhance
A6: Kadarkarai | B6: High | C6: In Progress | D6: Core Product | E6: CS 2.0 | F6: R26.Q2 | G6: Sprint 02 | H6: Design | I6: Platform | J6: Medium | K6: Medium | L6: Mitigating | M6: Satisfied | N6: Maintenance
A7: MJ | B7: Medium | C7: Completed | D7: Rewards | E7: CS 2.0 Achievo | F7: R26.Q3 | G7: Sprint 03 | H7: Build | I7: Data | J7: Low | K7: Low | L7: Watching | M7: Overdue | N7: New Features
A8: Shriguru | B8: Low | C8: At Risk | D8: Data & AI | E8: CS 2.0 Core | F8: R26.Q4 | G8: Sprint 04 | H8: Test | I8: Integrations | L8: Closed | M8: Waived | N8: PIS New Feature
A9: Siva | C9: Blocked | D9: Integrations | E9: CS 2.0 Data | F9: R27.Q1 | G9: Sprint 05 | H9: UAT | I9: Reliability | N9: Tech Enhance
D10: SRE / Support | E10: Unassigned | F10: R27.Q2 | G10: Sprint 06 | H10: Release | I10: Governance | N10: Tech Maintenance
D11: Architecture | F11: Hotfix | G11: Sprint 07 | H11: Hypercare | I11: Tech Debt
D12: Compliance Eng | F12: N/A | G12: Sprint 08
G13: Sprint 09
G14: Sprint 10
G15: Sprint 11
G16: Sprint 12
G17: Sprint 13
G18: Sprint 14
G19: Sprint 15
G20: Sprint 16
G21: Sprint 17
G22: Sprint 18
G23: Sprint 19
G24: Sprint 20
... G30: Sprint 26
